{
	"format_version": "1.8.0",
	"animations": {
		"short_sword_1": {
			"loop": "hold_on_last_frame",
			"animation_length": 0.52,
			"bones": {
				"Body": {
					"rotation": {
						"0.0": [0, 0, 0],
						"0.12": [0, 15, 0],
						"0.28": [17.6016, -12.47096, -0.66757],
						"0.32": [20.21893, -14.92678, -1.3422]
					},
					"position": {
						"0.0": [0, 0, 0],
						"0.12": [0, -0.25, 2],
						"0.28": [0, -1.25, -3],
						"0.32": [0, -1.25, -3]
					}
				},
				"LeftArm": {
					"rotation": {
						"0.0": [0, 0, 0],
						"0.12": [-30, 0, 12.5],
						"0.28": [24.3399, -14.20392, -0.035],
						"0.32": [23.09448, -16.21622, 4.70873]
					},
					"position": {
						"0.0": [0, 0, 0],
						"0.32": [0, 0, 0]
					}
				},
				"RightArm": {
					"rotation": {
						"0.0": [0, 0, 0],
						"0.12": [-140.65317, 46.16728, -28.83686],
						"0.28": [-13.52892, -7.29634, -66.95441],
						"0.32": [-25.14948, -1.64615, -70.648]
					},
					"position": {
						"0.0": [0, 0, 0],
						"0.12": [0, -1, 2],
						"0.28": [2, -1, -3],
						"0.32": [2.25, -1, -3]
					}
				},
				"LeftLeg": {
					"rotation": {
						"0.0": [0, 0, 0],
						"0.12": [-17.49526, -2.49048, -0.21803],
						"0.28": [5.06344, -0.9762, -7.43656],
						"0.32": [-7.32648, -2.86313, -6.93488]
					},
					"position": {
						"0.0": [0, 0, 0],
						"0.12": [0, 0, -2],
						"0.24": [0, 0.75, 0],
						"0.28": [0, 0, 1],
						"0.32": [0, 0, 1]
					}
				},
				"RightLeg": {
					"rotation": {
						"0.0": [0, 0, 0],
						"0.12": [10, 0, 0],
						"0.2": [-7.38733, 1.29876, 9.91615],
						"0.28": [-9.74687, -9.53274, -3.03513],
						"0.32": [-27.5, 0, 0]
					},
					"position": {
						"0.0": [0, 0, 0],
						"0.12": [0, 0, 1],
						"0.2": [-1, 2.67, -3],
						"0.28": [0, 1, -2],
						"0.32": [0, 1, -2.5]
					}
				}
			}
		},
		"short_sword_2": {
			"loop": "hold_on_last_frame",
			"animation_length": 0.52,
			"bones": {
				"Body": {
					"rotation": {
						"0.0": [20.21893, -14.92678, -1.3422],
						"0.24": [22.6262, 13.07816, 9.50539]
					},
					"position": {
						"0.0": [0, -1.25, -3],
						"0.24": [0, -1.25, -3]
					}
				},
				"LeftArm": {
					"rotation": {
						"0.0": [23.09448, -16.21622, 4.70873],
						"0.24": [-44.97723, -6.18694, -17.54072]
					},
					"position": {
						"0.0": [0, 0, 0],
						"0.24": [0, 0, 0]
					}
				},
				"RightArm": {
					"rotation": {
						"0.0": [-25.14948, -1.64615, -70.648],
						"0.04": [-75.424, 3.99396, 92.33381],
						"0.24": [34.576, 3.99396, 92.33381]
					},
					"position": {
						"0.0": [2.25, -1, -3],
						"0.24": [-0.75, -1, 1]
					}
				},
				"LeftLeg": {
					"rotation": {
						"0.0": [-7.32648, -2.86313, -6.93488],
						"0.24": [-42.9495, -27.76617, -4.6318]
					},
					"position": {
						"0.0": [0, 0, 1],
						"0.12": [0, 2.5, -1],
						"0.24": [0, 1, -1]
					}
				},
				"RightLeg": {
					"rotation": {
						"0.0": [-27.5, 0, 0],
						"0.24": [4.859, -20.06023, 2.49031]
					},
					"position": {
						"0.0": [0, 1, -2.5],
						"0.24": [1, -0.5, 1.25]
					}
				}
			}
		},
		"short_sword_3": {
			"loop": "hold_on_last_frame",
			"animation_length": 0.52,
			"bones": {
				"Body": {
					"rotation": {
						"0.0": [22.6262, 13.07816, 9.50539],
						"0.12": [-15, 0, 0],
						"0.32": [25, 0, 0]
					},
					"position": {
						"0.0": [0, -1.25, -3],
						"0.12": [0, -1.5, 4],
						"0.16": [0, 0.5, 3],
						"0.24": [0, 0.5, 0],
						"0.32": [0, -3.5, -4]
					}
				},
				"LeftArm": {
					"rotation": {
						"0.0": [-44.97723, -6.18694, -17.54072],
						"0.12": [21.31202, -7.57749, -8.41213],
						"0.32": [15.45617, -19.53811, -8.57888]
					},
					"position": {
						"0.0": [0, 0, 0],
						"0.12": [0, -1, 0],
						"0.32": [0, -1, 0]
					}
				},
				"RightArm": {
					"rotation": {
						"0.0": [34.576, 3.99396, 92.33381],
						"0.04": [-55.22035, 24.63979, 30.10024],
						"0.12": [-214.55056, 4.5778, -15.57755],
						"0.32": [-15.48951, -14.1151, 5.10291]
					},
					"position": {
						"0.0": [-0.75, -1, 1],
						"0.12": [-0.75, 1, 0],
						"0.32": [0.25, -1, -2]
					}
				},
				"LeftLeg": {
					"rotation": {
						"0.0": [-42.9495, -27.76617, -4.6318],
						"0.12": [12.5, 0, 0],
						"0.32": [0, 0, 0]
					},
					"position": {
						"0.0": [0, 1, -1],
						"0.12": [0, 0, 1],
						"0.16": [0, 0.5, 1],
						"0.24": [0, 0, 1],
						"0.32": [0, 1, 2]
					}
				},
				"RightLeg": {
					"rotation": {
						"0.0": [4.859, -20.06023, 2.49031],
						"0.12": [5, 0, 0],
						"0.32": [-35, 0, 0]
					},
					"position": {
						"0.0": [1, -0.5, 1.25],
						"0.12": [0, 0.75, -2.25],
						"0.16": [0, 2.67, -3.42],
						"0.24": [0, 0.5, -2.75],
						"0.32": [0, 2.5, -1.75]
					}
				}
			}
		},
		"short_sword_4": {
			"loop": "hold_on_last_frame",
			"animation_length": 0.6,
			"bones": {
				"Body": {
					"rotation": {
						"0.0": [25, 0, 0],
						"0.2": [-7.5, 0, 0],
						"0.48": [-7.56397, -7.43547, 0.98448],
						"0.6": [0, 0, 0]
					},
					"position": {
						"0.0": [0, -3.5, -4],
						"0.08": [0, -5, -4],
						"0.2": [0, -0.5, 0],
						"0.48": [0, -0.5, 0],
						"0.6": [0, 0, 0]
					}
				},
				"LeftArm": {
					"rotation": {
						"0.0": [15.45617, -19.53811, -8.57888],
						"0.2": [4.32548, -10.46248, -4.22598],
						"0.48": [29.32548, -10.46248, -4.22598],
						"0.6": [0, 0, 0]
					},
					"position": {
						"0.0": [0, -1, 0],
						"0.48": [0, -0.38, 0],
						"0.6": [0, 0, 0]
					}
				},
				"RightArm": {
					"rotation": {
						"0.0": [-15.48951, -14.1151, 5.10291],
						"0.2": [-129.32158, -16.796, 0.72347],
						"0.48": [-142.98951, -14.1151, 5.10291],
						"0.6": [0, 0, 0]
					},
					"position": {
						"0.0": [0.25, -1, -2],
						"0.2": [0.1, 1.62, -0.77],
						"0.48": [0.1, 1.62, -0.77],
						"0.6": [0, 0, 0]
					}
				},
				"LeftLeg": {
					"rotation": {
						"0.0": [0, 0, 0],
						"0.2": [27.5, 0, 0],
						"0.48": [27.5, 0, 0],
						"0.6": [0, 0, 0]
					},
					"position": {
						"0.0": [0, 1, 2],
						"0.08": [0, 2, 2],
						"0.2": [0, 1, 2],
						"0.48": [0, 1, 2],
						"0.6": [0, 0, 0]
					}
				},
				"RightLeg": {
					"rotation": {
						"0.0": [-35, 0, 0],
						"0.2": [-10, 0, 0],
						"0.48": [-10, 0, 0],
						"0.6": [0, 0, 0]
					},
					"position": {
						"0.0": [0, 2.5, -1.75],
						"0.08": [0, 3.5, -1.75],
						"0.2": [0, 0.5, -1.75],
						"0.48": [0, 0.5, -1.75],
						"0.6": [0, 0, 0]
					}
				}
			}
		},
		"short_sword_5": {
			"loop": "hold_on_last_frame",
			"animation_length": 0.52,
			"bones": {
				"Body": {
					"rotation": {
						"0.0": [-7.56397, -7.43547, 0.98448],
						"0.28": [37.43603, -7.43547, 0.98448]
					},
					"position": {
						"0.0": [0, -0.5, 0],
						"0.28": [0, -3.5, -6]
					}
				},
				"LeftArm": {
					"rotation": {
						"0.0": [4.32548, -10.46248, -4.22598],
						"0.28": [31.82548, -10.46248, -4.22598]
					},
					"position": {
						"0.0": [0, -0.38, 0],
						"0.28": [0, -1.38, 0]
					}
				},
				"RightArm": {
					"rotation": {
						"0.0": [-142.98951, -14.1151, 5.10291],
						"0.28": [-50.48951, -14.1151, 5.10291]
					},
					"position": {
						"0.0": [0.1, 1.62, -0.77],
						"0.28": [0, 0, -2]
					}
				},
				"LeftLeg": {
					"rotation": {
						"0.0": [27.5, 0, 0],
						"0.28": [-17.5, 0, 0]
					},
					"position": {
						"0.0": [0, 1, 2],
						"0.28": [0, 0, 1]
					}
				},
				"RightLeg": {
					"rotation": {
						"0.0": [-10, 0, 0],
						"0.28": [-67.5, 0, 0]
					},
					"position": {
						"0.0": [0, 0.5, -1.75],
						"0.28": [0, 0.25, -0.75]
					}
				}
			}
		},
		"short_sword_6": {
			"loop": true,
			"bones": {
				"Body": {
					"rotation": [37.43603, -7.43547, 0.98448],
					"position": [0, -3.5, -6]
				},
				"LeftArm": {
					"rotation": [31.82548, -10.46248, -4.22598],
					"position": [0, -1.38, 0]
				},
				"RightArm": {
					"rotation": [-50.48951, -14.1151, 5.10291],
					"position": [0, 0, -2]
				},
				"LeftLeg": {
					"rotation": [-17.5, 0, 0],
					"position": [0, 0, 1]
				},
				"RightLeg": {
					"rotation": [-67.5, 0, 0],
					"position": [0, 0.25, -0.75]
				}
			}
		},
		"short_sword_use": {
			"animation_length": 0.8,
			"bones": {
				"Body": {
					"rotation": {
						"0.0": [0, 0, 0],
						"0.12": [10, 10, 0],
						"0.2": [20, 10, 0],
						"0.24": [11.76205, 7.84962, -0.34488],
						"0.36": [-4.08869, -8.57515, -0.17434],
						"0.48": [-20, -7.5, 0],
						"0.8": [0, 0, 0]
					},
					"position": {
						"0.0": [0, 0, 0],
						"0.04": [0, -1.33, 0],
						"0.12": [0, 0, 0],
						"0.2": [0, -3, -3],
						"0.36": [-0.57, -1, -0.14],
						"0.48": [-1, 0.25, 2],
						"0.8": [0, 0, 0]
					}
				},
				"LeftArm": {
					"rotation": {
						"0.0": [0, 0, 0],
						"0.12": [-12.5, 0, 0],
						"0.2": [-12.39638, -1.61888, -12.32417],
						"0.48": [47.5, 0, 0],
						"0.8": [0, 0, 0]
					},
					"position": {
						"0.0": [0, 0, 0],
						"0.8": [0, 0, 0]
					}
				},
				"RightArm": {
					"rotation": {
						"0.0": [0, 0, 0],
						"0.12": [-40, 0, 0],
						"0.2": [-45, 0, 0],
						"0.32": [-53.21, 0, 0],
						"0.48": [-122.5, 0, 0],
						"0.8": [0, 0, 0]
					},
					"position": {
						"0.0": [0, 0, 0],
						"0.12": [0, -1, 0],
						"0.2": [0, -1, 0],
						"0.48": [0, 1.47, 0],
						"0.8": [0, 0, 0]
					}
				},
				"LeftLeg": {
					"rotation": {
						"0.0": [0, 0, 0],
						"0.12": [-2.5, -12.5, 0],
						"0.2": [30, -12.5, 0],
						"0.36": [18.92857, -12.5, 0],
						"0.48": [52.5, -12.5, 0],
						"0.8": [0, 0, 0]
					},
					"position": {
						"0.0": [0, 0, 0],
						"0.04": [0, 1, 0.33],
						"0.12": [0, 0, 1],
						"0.2": [0, 1, 1],
						"0.48": [0, 2, 1],
						"0.8": [0, 0, 0]
					}
				},
				"RightLeg": {
					"rotation": {
						"0.0": [0, 0, 0],
						"0.12": [-22.5, -7.5, 0],
						"0.2": [-52.5, -7.5, 0],
						"0.48": [27.5, -7.5, 0],
						"0.8": [0, 0, 0]
					},
					"position": {
						"0.0": [0, 0, 0],
						"0.04": [0, 1.67, -0.33],
						"0.12": [0, 2, -2],
						"0.2": [0, 1, -1],
						"0.48": [0, 0, -1],
						"0.8": [0, 0, 0]
					}
				}
			}
		},
		"long_sword_1": {
			"loop": "hold_on_last_frame",
			"animation_length": 0.8,
			"bones": {
				"Body": {
					"rotation": {
						"0.0": [0, 0, 0],
						"0.28": [2.68789, -27.48982, -0.48922],
						"0.56": [2.63004, 24.96124, 1.86273]
					},
					"position": {
						"0.0": [0, 0, 0],
						"0.56": [0, 0, 0]
					}
				},
				"LeftArm": {
					"rotation": {
						"0.0": [0, 0, 0],
						"0.28": [-46.30791, 10.51063, 7.44282],
						"0.44": [-26.39457, -11.50802, 53.89904],
						"0.52": [-14.92872, -25.79416, 70.21381],
						"0.56": [-5.41582, -33.83085, 71.1392]
					},
					"position": {
						"0.0": [0, 0, 0],
						"0.28": [1, -3, 2],
						"0.4": [-4.14, -3, 0.29],
						"0.52": [-4.03, -2, -1.43],
						"0.56": [-5, -3, -2]
					}
				},
				"RightArm": {
					"rotation": {
						"0.0": [0, 0, 0],
						"0.28": [-61.36354, -74.41364, 7.44024],
						"0.56": [17.60538, 7.80081, 64.88423]
					},
					"position": {
						"0.0": [0, 0, 0],
						"0.28": [3, -1, -2],
						"0.56": [2, -1, -4]
					}
				},
				"LeftLeg": {
					"rotation": {
						"0.0": [0, 0, 0],
						"0.28": [9.91193, 14.98539, -0.66963],
						"0.56": [10.65265, -22.62074, -1.32624]
					},
					"position": {
						"0.0": [0, 0, 0],
						"0.28": [2, 0, 0],
						"0.56": [1, 0, 1]
					}
				},
				"RightLeg": {
					"rotation": {
						"0.0": [0, 0, 0],
						"0.28": [-22.70569, 22.47741, -1.03509],
						"0.56": [-12.33581, -32.73032, 0.90553]
					},
					"position": {
						"0.0": [0, 0, 0],
						"0.28": [-1, 0, -1],
						"0.56": [0, 0, -2]
					}
				}
			}
		},
		"long_sword_2": {
			"loop": "hold_on_last_frame",
			"animation_length": 0.8,
			"bones": {
				"Body": {
					"rotation": {
						"0.0": [2.63004, 24.96124, 1.86273],
						"0.24": [-7.36996, 24.96124, 1.86273],
						"0.52": [5.40377, -19.7161, 7.39194]
					},
					"position": {
						"0.0": [0, 0, 0],
						"0.24": [2, 0, 2.75],
						"0.52": [4, 0, -2]
					}
				},
				"LeftArm": {
					"rotation": {
						"0.0": [-5.41582, -33.83085, 71.1392],
						"0.24": [-8.60271, 41.05738, 103.61614],
						"0.36": [-46.12512, -2.31186, 74.1199],
						"0.44": [-66.26989, -17.64252, 69.93008],
						"0.52": [-114.12342, 1.36049, 119.72309]
					},
					"position": {
						"0.0": [-5, -3, -2],
						"0.24": [-5, -3, -1],
						"0.52": [-1, -3, 5]
					},
					"scale": {
						"0.0": [1, 1, 1],
						"0.24": [1, 1.2, 1],
						"0.52": [1, 1, 1]
					}
				},
				"RightArm": {
					"rotation": {
						"0.0": [17.60538, 7.80081, 64.88423],
						"0.24": [-140.65317, 46.16728, -33.83686],
						"0.52": [-10.35489, -11.4873, -68.85863]
					},
					"position": {
						"0.0": [2, -1, -4],
						"0.24": [0, -1, 2],
						"0.52": [3, -1, -3]
					}
				},
				"LeftLeg": {
					"rotation": {
						"0.0": [10.65265, -22.62074, -1.32624],
						"0.52": [-6.89219, -7.62163, -1.15582]
					},
					"position": {
						"0.0": [1, 0, 1],
						"0.24": [1, 0, 2],
						"0.52": [1, 0, 0]
					}
				},
				"RightLeg": {
					"rotation": {
						"0.0": [-12.33581, -32.73032, 0.90553],
						"0.24": [-2.33581, -32.73032, 0.90553],
						"0.52": [18.01711, -7.7474, -0.0905]
					},
					"position": {
						"0.0": [0, 0, -2],
						"0.24": [0, 1, -3],
						"0.36": [0, 1, -3],
						"0.52": [0, 0, 2]
					}
				}
			}
		},
		"long_sword_3": {
			"loop": "hold_on_last_frame",
			"animation_length": 0.8,
			"bones": {
				"Body": {
					"rotation": {
						"0.0": [5.40377, -19.7161, 7.39194],
						"0.24": [-20, 0, 0],
						"0.56": [35, 0, 0]
					},
					"position": {
						"0.0": [4, 0, -2],
						"0.24": [0, -0.5, 3],
						"0.56": [0, -1, -6]
					}
				},
				"Head": {
					"rotation": {
						"0.0": [0, 0, 0],
						"0.08": [7.5, 0, 0],
						"0.56": [0, 0, 0]
					},
					"position": {
						"0.0": [0, 0, 0],
						"0.24": [0, 0.5, 1.5],
						"0.56": [0, 0, 0]
					}
				},
				"LeftArm": {
					"rotation": {
						"0.0": [-114.12342, 1.36049, 119.72309],
						"0.04": [-86.58529, -12.54446, 87.39331],
						"0.12": [-99.44343, 27.00108, 22.74803],
						"0.24": [-185.24765, 15.7627, -37.15736],
						"0.56": [-27.3645, 36.5205, 2.8008]
					},
					"position": {
						"0.0": [-1, -3, 5],
						"0.04": [-1.67, -2.33, -0.5],
						"0.24": [-5, 1, -4],
						"0.56": [-4, -3, -2]
					}
				},
				"RightArm": {
					"rotation": {
						"0.0": [-10.35489, -11.4873, -68.85863],
						"0.08": [-110.42109, -19.76236, 37.83531],
						"0.24": [-162.5, 0, 0],
						"0.56": [-31.58371, -13.35049, -6.37821]
					},
					"position": {
						"0.0": [3, -1, -3],
						"0.24": [0, 3, -1],
						"0.56": [0, -2, -2]
					}
				},
				"LeftLeg": {
					"rotation": {
						"0.0": [-6.89219, -7.62163, -1.15582],
						"0.24": [23.10781, -7.62163, -1.15582],
						"0.56": [13.10781, -7.62163, -1.15582]
					},
					"position": {
						"0.0": [1, 0, 0],
						"0.24": [1, 0, 1],
						"0.56": [1, 0, 0]
					}
				},
				"RightLeg": {
					"rotation": {
						"0.0": [18.01711, -7.7474, -0.0905],
						"0.24": [18.01711, -7.7474, -0.0905],
						"0.56": [-41.98289, -7.7474, -0.0905]
					},
					"position": {
						"0.0": [0, 0, 2],
						"0.24": [0, 1, -2],
						"0.56": [0, 0, -2]
					}
				}
			}
		},
		"long_sword_4": {
			"loop": true,
			"bones": {
				"Body": {
					"rotation": [35, 0, 0],
					"position": [0, -1, -6]
				},
				"Head": {
					"rotation": [0, 0, 0],
					"position": [0, 0, 0]
				},
				"LeftArm": {
					"rotation": [-27.3645, 36.5205, 2.8008],
					"position": [-4, -3, -2]
				},
				"RightArm": {
					"rotation": [-31.58371, -13.35049, -6.37821],
					"position": [0, -2, -2]
				},
				"LeftLeg": {
					"rotation": [13.10781, -7.62163, -1.15582],
					"position": [1, 0, 0]
				},
				"RightLeg": {
					"rotation": [-41.98289, -7.7474, -0.0905],
					"position": [0, 0, -2]
				}
			}
		},
		"long_sword_use": {
			"loop": "hold_on_last_frame",
			"animation_length": 0.76,
			"bones": {
				"Body": {
					"rotation": {
						"0.0": [0, 0, 0],
						"0.08": [3.00486, -37.47758, -1.07717],
						"0.2": [2.68789, -27.48982, -0.48922],
						"0.56": [-5.97461, 69.87706, -2.5534]
					},
					"position": {
						"0.0": [0, 0, 0],
						"0.08": [0, 0, -1.4],
						"0.2": [0, -1, -1],
						"0.4": [-0.33, 0.33, -1],
						"0.56": [-1, 0, -1]
					}
				},
				"LeftArm": {
					"rotation": {
						"0.0": [0, 0, 0],
						"0.08": [-47.33108, 14.71489, 10.41995],
						"0.2": [-47.33108, 14.71489, 10.41995],
						"0.28": [-32.98212, 17.71259, 34.79426],
						"0.36": [-13.38427, 21.5696, 66.64766],
						"0.44": [1.71927, 21.80221, 94.86755],
						"0.56": [14.35939, 22.02693, 110.27094]
					},
					"position": {
						"0.0": [0, 0, 0],
						"0.08": [1, -3, 4],
						"0.2": [1, -3, 3],
						"0.28": [-2, -3, 1.11],
						"0.36": [-3.71, -2, -1.49],
						"0.52": [-7.14, -1.8, -1.1],
						"0.56": [-8, -3, -1]
					}
				},
				"RightArm": {
					"rotation": {
						"0.0": [0, 0, 0],
						"0.08": [-165.95334, -74.47142, 112.11428],
						"0.2": [-61.36354, -74.41364, 7.44024],
						"0.56": [52.27213, 67.09221, 159.75265]
					},
					"position": {
						"0.0": [0, 0, 0],
						"0.08": [4, -1, -2],
						"0.2": [3, -1, -2],
						"0.56": [0, -1, 0]
					}
				},
				"LeftLeg": {
					"rotation": {
						"0.0": [0, 0, 0],
						"0.08": [10.35871, 22.36873, 0.72258],
						"0.2": [9.91193, 14.98539, -0.66963],
						"0.56": [14.812, -34.75443, -4.76283]
					},
					"position": {
						"0.0": [0, 0, 0],
						"0.08": [2, 0, 0],
						"0.2": [2, 0, -1],
						"0.4": [2, 1, 1.22],
						"0.56": [2, 0, 3]
					}
				},
				"RightLeg": {
					"rotation": {
						"0.0": [0, 0, 0],
						"0.08": [-24.1572, 29.36104, -4.34912],
						"0.2": [-22.70569, 22.47741, -1.03509],
						"0.56": [-8.39561, -42.63712, 2.63264]
					},
					"position": {
						"0.0": [0, 0, 0],
						"0.08": [-1, 0, -1],
						"0.2": [-1, 0, -1],
						"0.4": [0.11, 1, -2.11],
						"0.56": [1, 0, -3]
					}
				},
				"Head": {
					"rotation": {
						"0.0": [0, 0, 0],
						"0.2": [7.67995, -12.39135, -1.6575],
						"0.56": [-7.55034, 9.97848, -0.33122]
					}
				}
			}
		},
		"spear_1": {
			"loop": "hold_on_last_frame",
			"animation_length": 0.6,
			"bones": {
				"Body": {
					"rotation": {
						"0.0": [0, 0, 0],
						"0.24": [-4.98107, -44.78238, 7.05323],
						"0.36": [18.14331, -37.59246, 9.89551]
					},
					"position": {
						"0.0": [0, 0, 0],
						"0.24": [0, -1, 2.75],
						"0.36": [4, -2, -4]
					}
				},
				"Head": {
					"position": {
						"0.0": [0, 0, 0],
						"0.24": [0, 0, -0.67],
						"0.36": [0, 0, -2]
					}
				},
				"LeftArm": {
					"rotation": {
						"0.0": [0, 0, 0],
						"0.24": [-18.84415, 11.48971, 14.35646],
						"0.36": [-52.6828, 22.12719, 14.3938]
					},
					"position": {
						"0.0": [0, 0, 0],
						"0.24": [0, 0, 0.33],
						"0.36": [-3, 0, -1]
					}
				},
				"RightArm": {
					"rotation": {
						"0.0": [0, 0, 0],
						"0.24": [-30.4833, 22.10059, -55.37616],
						"0.28": [-47.13765, 11.08658, -49.46377],
						"0.36": [-53.89692, 6.86844, -51.82094]
					},
					"position": {
						"0.0": [0, 0, 0],
						"0.24": [2, -1, -1],
						"0.36": [0, 0, -4]
					}
				},
				"LeftLeg": {
					"rotation": {
						"0.0": [0, 0, 0],
						"0.24": [-3.03842, 20.47142, -10.19895],
						"0.36": [-5.12116, 17.48281, -3.28795]
					},
					"position": {
						"0.0": [0, 0, 0],
						"0.24": [0, 1, -0.5],
						"0.36": [3.5, 0, 1.5]
					}
				},
				"RightLeg": {
					"rotation": {
						"0.0": [0, 0, 0],
						"0.24": [-4.99889, 28.80363, -4.91436],
						"0.36": [-57.5, 0, 0]
					},
					"position": {
						"0.0": [0, 0, 0],
						"0.24": [0, 0, -0.5],
						"0.36": [-2, -0.5, -1.5]
					}
				},
				"RightItem": {
					"rotation": {
						"0.0": [0, 0, 0],
						"0.24": [6.69304, 9.30727, 20.57639],
						"0.28": [-1.23022, 6.98045, 15.43229],
						"0.36": [5.56431, -7.43547, 29.14743]
					},
					"position": {
						"0.0": [0, 0, 0],
						"0.24": [2, -1, 2],
						"0.36": [3, -1, 0]
					}
				}
			}
		},
		"spear_2": {
			"loop": "hold_on_last_frame",
			"animation_length": 0.52,
			"bones": {
				"Body": {
					"rotation": {
						"0.0": [18.14331, -37.59246, 9.89551],
						"0.16": [18.14331, -37.59246, 9.89551],
						"0.32": [-21.46883, -8.65914, 1.82918]
					},
					"position": {
						"0.0": [4, -2, -4],
						"0.16": [4, -2, -7],
						"0.32": [-2, -1.75, 4]
					}
				},
				"Head": {
					"rotation": {
						"0.0": [0, 0, 0],
						"0.16": [-2.82678, 32.48404, -0.76684],
						"0.32": [0, 0, 0]
					},
					"position": {
						"0.0": [0, 0, -2],
						"0.16": [0, 0, -2],
						"0.32": [0, 0, 0]
					}
				},
				"LeftArm": {
					"rotation": {
						"0.0": [-52.6828, 22.12719, 14.3938],
						"0.16": [-61.62574, 26.54904, 16.95646],
						"0.32": [-123.09591, 52.95883, -13.60747]
					},
					"position": {
						"0.0": [-3, 0, -1],
						"0.16": [-4, -1, -2],
						"0.32": [-4, 2, -4]
					}
				},
				"RightArm": {
					"rotation": {
						"0.0": [-53.89692, 6.86844, -51.82094],
						"0.16": [-66.39692, 6.86844, -51.82094],
						"0.24": [-93.97904, 6.02164, -12.98576],
						"0.32": [-123.53206, 3.61148, 5.81353]
					},
					"position": {
						"0.0": [0, 0, -4],
						"0.16": [0, 0, -4],
						"0.32": [1, 5, -3]
					}
				},
				"LeftLeg": {
					"rotation": {
						"0.0": [-5.12116, 17.48281, -3.28795],
						"0.16": [-13.86335, 15.95433, -16.24449],
						"0.32": [24.87884, 17.48281, -3.28795]
					},
					"position": {
						"0.0": [3.5, 0, 1.5],
						"0.16": [3.5, 1, 1.5],
						"0.32": [3.5, 1.5, 1]
					}
				},
				"RightLeg": {
					"rotation": {
						"0.0": [-57.5, 0, 0],
						"0.16": [-57.5, 0, 0],
						"0.32": [7.5, 0, 0]
					},
					"position": {
						"0.0": [-2, -0.5, -1.5],
						"0.16": [-2, -0.5, -1.5],
						"0.32": [-2, 0.5, -0.5]
					}
				},
				"RightItem": {
					"rotation": {
						"0.0": [5.56431, -7.43547, 29.14743],
						"0.12": [3.25449, -0.72108, 12.47952],
						"0.16": [-2.28366, -13.83448, 28.06869],
						"0.32": [0, 0, 0]
					},
					"position": {
						"0.0": [3, -1, 0],
						"0.12": [2, -1, 0],
						"0.16": [3, -2, 0],
						"0.32": [0, 1, 0]
					}
				}
			}
		},
		"spear_3": {
			"loop": "hold_on_last_frame",
			"animation_length": 0.6,
			"bones": {
				"Body": {
					"rotation": {
						"0.0": [-21.46883, -8.65914, 1.82918],
						"0.24": [-4.98107, -44.78238, 7.05323],
						"0.36": [18.14331, -37.59246, 9.89551]
					},
					"position": {
						"0.0": [-2, -1.75, 4],
						"0.24": [0, -1, 2.75],
						"0.36": [4, -2, -4]
					}
				},
				"Head": {
					"rotation": {
						"0.0": [0, 0, 0],
						"0.24": [0, 17.5, 0],
						"0.36": [-2.82678, 32.48404, -0.76684]
					},
					"position": {
						"0.0": [0, 0, 0],
						"0.24": [0, 0, -0.67],
						"0.36": [0, 0, -2]
					}
				},
				"LeftArm": {
					"rotation": {
						"0.0": [-123.09591, 52.95883, -13.60747],
						"0.24": [-18.84415, 11.48971, 14.35646],
						"0.36": [-52.6828, 22.12719, 14.3938]
					},
					"position": {
						"0.0": [-4, 2, -4],
						"0.24": [0, 0, 0.33],
						"0.36": [-3, 0, -1]
					}
				},
				"RightArm": {
					"rotation": {
						"0.0": [-123.53206, 3.61148, 5.81353],
						"0.24": [-30.4833, 22.10059, -55.37616],
						"0.28": [-47.13765, 11.08658, -49.46377],
						"0.36": [-53.89692, 6.86844, -51.82094]
					},
					"position": {
						"0.0": [1, 5, -3],
						"0.24": [2, -1, -1],
						"0.36": [0, 0, -4]
					}
				},
				"LeftLeg": {
					"rotation": {
						"0.0": [24.87884, 17.48281, -3.28795],
						"0.24": [-3.03842, 20.47142, -10.19895],
						"0.36": [-5.12116, 17.48281, -3.28795]
					},
					"position": {
						"0.0": [3.5, 1.5, 1],
						"0.24": [0, 1, -0.5],
						"0.36": [3.5, 0, 1.5]
					}
				},
				"RightLeg": {
					"rotation": {
						"0.0": [7.5, 0, 0],
						"0.24": [-4.99889, 28.80363, -4.91436],
						"0.36": [-57.5, 0, 0]
					},
					"position": {
						"0.0": [-2, 0.5, -0.5],
						"0.24": [0, 0, -0.5],
						"0.36": [-2, -0.5, -1.5]
					}
				},
				"RightItem": {
					"rotation": {
						"0.0": [0, 0, 0],
						"0.24": [0.01453, 9.34187, 25.64326],
						"0.28": [-1.23022, 6.98045, 15.43229],
						"0.36": [5.56431, -7.43547, 29.14743]
					},
					"position": {
						"0.0": [0, 1, 0],
						"0.24": [3, -1, 2],
						"0.36": [3, -1, 0]
					}
				}
			}
		},
		"spear_4": {
			"loop": "hold_on_last_frame",
			"animation_length": 0.6,
			"bones": {
				"Body": {
					"rotation": {
						"0.0": [18.14331, -37.59246, 9.89551],
						"0.24": [-4.98107, -44.78238, 7.05323],
						"0.36": [18.14331, -37.59246, 9.89551]
					},
					"position": {
						"0.0": [4, -2, -4],
						"0.24": [0, -1, 2.75],
						"0.36": [4, -2, -4]
					}
				},
				"Head": {
					"rotation": {
						"0.0": [-2.82678, 32.48404, -0.76684],
						"0.24": [0, 17.5, 0],
						"0.36": [-2.82678, 32.48404, -0.76684]
					},
					"position": {
						"0.0": [0, 0, -2],
						"0.24": [0, 0, -0.67],
						"0.36": [0, 0, -2]
					}
				},
				"LeftArm": {
					"rotation": {
						"0.0": [-52.6828, 22.12719, 14.3938],
						"0.24": [-18.84415, 11.48971, 14.35646],
						"0.36": [-57.6828, 22.12719, 14.3938]
					},
					"position": {
						"0.0": [-3, 0, -1],
						"0.24": [0, 0, 0.33],
						"0.36": [-3, 0, -2]
					}
				},
				"RightArm": {
					"rotation": {
						"0.0": [-53.89692, 6.86844, -51.82094],
						"0.24": [-30.4833, 22.10059, -55.37616],
						"0.28": [-47.13765, 11.08658, -49.46377],
						"0.36": [-65.78255, -0.52094, -46.66122]
					},
					"position": {
						"0.0": [0, 0, -4],
						"0.24": [2, -1, -1],
						"0.36": [0, 0, -4]
					}
				},
				"LeftLeg": {
					"rotation": {
						"0.0": [-5.12116, 17.48281, -3.28795],
						"0.24": [-3.03842, 20.47142, -10.19895],
						"0.36": [-5.12116, 17.48281, -3.28795]
					},
					"position": {
						"0.0": [3.5, 0, 1.5],
						"0.24": [0, 1, -0.5],
						"0.36": [3.5, 0, 1.5]
					}
				},
				"RightLeg": {
					"rotation": {
						"0.0": [-57.5, 0, 0],
						"0.24": [-4.99889, 28.80363, -4.91436],
						"0.36": [-57.5, 0, 0]
					},
					"position": {
						"0.0": [-2, -0.5, -1.5],
						"0.24": [0, 0, -0.5],
						"0.36": [-2, 0.5, -2.5]
					}
				},
				"RightItem": {
					"rotation": {
						"0.0": [5.56431, -7.43547, 29.14743],
						"0.24": [0.01453, 9.34187, 25.64326],
						"0.28": [-1.23022, 6.98045, 15.43229],
						"0.36": [10.2335, -7.88679, 31.62851]
					},
					"position": {
						"0.0": [3, -1, 0],
						"0.24": [3, -1, 2],
						"0.36": [3.2, -1.35, -1]
					}
				}
			}
		},
		"spear_5": {
			"loop": true,
			"bones": {
				"Body": {
					"rotation": [18.14331, -37.59246, 9.89551],
					"position": [4, -2, -4]
				},
				"Head": {
					"rotation": [-2.82678, 32.48404, -0.76684],
					"position": [0, 0, -2]
				},
				"LeftArm": {
					"rotation": [-57.6828, 22.12719, 14.3938],
					"position": [-3, 0, -2]
				},
				"RightArm": {
					"rotation": [-68.28255, -0.52094, -46.66122],
					"position": [0, 0, -4]
				},
				"LeftLeg": {
					"rotation": [-5.12116, 17.48281, -3.28795],
					"position": [3.5, 0, 1.5]
				},
				"RightLeg": {
					"rotation": [-57.5, 0, 0],
					"position": [-2, 0.5, -2.5]
				},
				"RightItem": {
					"rotation": [14.89149, -9.29798, 31.28223],
					"position": [3, -2, 0]
				}
			}
		},
		"spear_use": {
			"animation_length": 0.48,
			"bones": {
				"Body": {
					"rotation": {
						"0.0": [0, 0, 0],
						"0.12": [-4.98107, -44.78238, 7.05323],
						"0.24": [15.64331, -37.59246, 9.89551],
						"0.36": [7.82, -18.8, 4.95],
						"0.48": [0, 12.5, 0]
					},
					"position": {
						"0.0": [0, 0, 0],
						"0.12": [0, -1, 2.75],
						"0.24": [4, -2, -4],
						"0.36": [2, -1, -2],
						"0.48": [0.55, 0, 1.11]
					}
				},
				"Head": {
					"position": {
						"0.0": [0, 0, 0],
						"0.12": [0, 0, -0.67],
						"0.24": [0, 0, -2],
						"0.36": [0, 0, -1],
						"0.48": [0, 0, 0]
					}
				},
				"LeftArm": {
					"rotation": {
						"0.0": [0, 0, 0],
						"0.12": [-18.84415, 11.48971, 14.35646],
						"0.24": [-52.6828, 22.12719, 14.3938],
						"0.36": [-26.34, 11.06, 7.2],
						"0.48": [-11.11, 0, 0]
					},
					"position": {
						"0.0": [0, 0, 0],
						"0.12": [0, 0, 0.33],
						"0.24": [-3, 0, -1],
						"0.36": [-1.5, 0, -0.5],
						"0.48": [0, 0, 0]
					}
				},
				"RightArm": {
					"rotation": {
						"0.0": [0, 0, 0],
						"0.12": [-30.4833, 22.10059, -55.37616],
						"0.16": [-49.05792, 17.77553, -57.14511],
						"0.2": [-49.86267, 1.17786, -40.87309],
						"0.24": [-53.89692, 6.86844, -51.82094],
						"0.48": [26.15, -4.09, 3.77]
					},
					"position": {
						"0.0": [0, 0, 0],
						"0.12": [2, -1, -1],
						"0.24": [0, 0, -3],
						"0.48": [0, 0, 0.55]
					}
				},
				"LeftLeg": {
					"rotation": {
						"0.0": [0, 0, 0],
						"0.12": [-3.03842, 20.47142, -10.19895],
						"0.24": [-15.12116, 17.48281, -3.28795],
						"0.36": [-7.56, 8.74, -1.64],
						"0.48": [-4.17, 0, 0]
					},
					"position": {
						"0.0": [0, 0, 0],
						"0.12": [0, 1, -0.5],
						"0.24": [3.5, 0, 1.5],
						"0.36": [1.75, 0, 0.75],
						"0.48": [0, 0, 0]
					}
				},
				"RightLeg": {
					"rotation": {
						"0.0": [0, 0, 0],
						"0.12": [-4.99889, 28.80363, -4.91436],
						"0.24": [-45, 0, 0],
						"0.36": [-22.5, 0, 0],
						"0.48": [13.89, 0, 0]
					},
					"position": {
						"0.0": [0, 0, 0],
						"0.12": [0, 0, -0.5],
						"0.24": [-2, -0.5, -1.5],
						"0.36": [-1, -0.25, -0.75],
						"0.48": [0, 0, 0]
					}
				},
				"RightItem": {
					"rotation": {
						"0.0": [0, 0, 0],
						"0.12": [6.69304, 9.30727, 20.57639],
						"0.16": [-1.23022, 6.98045, 15.43229],
						"0.24": [15, 0, 0],
						"0.36": [7.5, 0, 0],
						"0.48": [-26.57, 0.67, -0.13]
					},
					"position": {
						"0.0": [0, 0, 0],
						"0.12": [2, -1, 2],
						"0.24": [0, 1, 0],
						"0.36": [0, 0.5, 0],
						"0.48": [0, -1.67, 2.22]
					}
				}
			}
		},
		"spear_use_continue": {
			"loop": true,
			"animation_length": 0.4,
			"bones": {
				"Body": {
					"rotation": {
						"0.0": [7.82, -18.8, 4.95],
						"0.16": [15.64331, -37.59246, 9.89551],
						"0.32": [7.82, -18.8, 4.95],
						"0.4": [0, 12.5, 0]
					},
					"position": {
						"0.0": [2, -1, -2],
						"0.16": [4, -2, -4],
						"0.32": [2, -1, -2],
						"0.4": [0.55, 0, 1.11]
					}
				},
				"Head": {
					"position": {
						"0.0": [0, 0, -1],
						"0.16": [0, 0, -2],
						"0.32": [0, 0, -1]
					}
				},
				"LeftArm": {
					"rotation": {
						"0.0": [-26.34, 11.06, 7.2],
						"0.16": [-52.6828, 22.12719, 14.3938],
						"0.32": [-26.34, 11.06, 7.2],
						"0.4": [-11.11, 0, 0]
					},
					"position": {
						"0.0": [-1.5, 0, -0.5],
						"0.16": [-3, 0, -3],
						"0.32": [-1.5, 0, -0.5],
						"0.4": [0, 0, 0]
					}
				},
				"RightArm": {
					"rotation": {
						"0.0": [-30.4833, 22.10059, -55.37616],
						"0.08": [-49.05792, 17.77553, -57.14511],
						"0.16": [-71.39692, 6.86844, -51.82094],
						"0.32": [-35.93, 4.58, -34.55],
						"0.4": [26.15, -4.09, 3.77]
					},
					"position": {
						"0.0": [2, -1, -1],
						"0.16": [0, 0, -4],
						"0.32": [0, 0, -2],
						"0.4": [0, 0, 0.55]
					}
				},
				"LeftLeg": {
					"rotation": {
						"0.0": [-7.56, 8.74, -1.64],
						"0.16": [-15.12116, 17.48281, -3.28795],
						"0.32": [-7.56, 8.74, -1.64],
						"0.4": [-4.17, 0, 0]
					},
					"position": {
						"0.0": [1.75, 0, 0.75],
						"0.16": [3.5, 0, 1.5],
						"0.32": [1.75, 0, 0.75],
						"0.4": [0, 0, 0]
					}
				},
				"RightLeg": {
					"rotation": {
						"0.0": [-22.5, 0, 0],
						"0.16": [-45, 0, 0],
						"0.32": [-22.5, 0, 0],
						"0.4": [13.89, 0, 0]
					},
					"position": {
						"0.0": [-1, -0.25, -0.75],
						"0.16": [-2, -0.5, -1.5],
						"0.32": [-1, -0.25, -0.75],
						"0.4": [0, 0, 0]
					}
				},
				"RightItem": {
					"rotation": {
						"0.0": [7.5, 0, 0],
						"0.08": [-1.30378, -20.51309, 16.03876],
						"0.16": [27.62113, -12.19908, 21.99054],
						"0.32": [7.5, 0, 0],
						"0.4": [-26.57, 0.67, -0.13]
					},
					"position": {
						"0.0": [0, 0.5, 0],
						"0.08": [1, -1.25, 0],
						"0.16": [3, -2, -1],
						"0.32": [0, 0.5, 0],
						"0.4": [0, -1.67, 2.22]
					}
				}
			}
		},
		"spear_use_finisher": {
			"animation_length": 0.8,
			"bones": {
				"Body": {
					"rotation": {
						"0.0": [0, 12.5, 0],
						"0.12": [0, 22.5, 0],
						"0.24": [0, 27.5, 0],
						"0.44": [19.22522, -41.4416, -8.39021],
						"0.52": [20.86942, -46.13948, -10.76398],
						"0.68": [0, 0, 0]
					},
					"position": {
						"0.0": [0.55, 0, 1.11],
						"0.12": [1, 0, 2],
						"0.24": [1, 0, 2],
						"0.44": [0, -1, -5],
						"0.52": [0, -1, -5],
						"0.68": [0, 0, 0]
					}
				},
				"LeftArm": {
					"rotation": {
						"0.0": [-11.11, 0, 0],
						"0.12": [-20, 0, 0],
						"0.24": [-20, 0, 0],
						"0.44": [35, 0, 0],
						"0.52": [37.5, 0, 0],
						"0.68": [0, 0, 0]
					},
					"position": {
						"0.0": [0, 0, 0],
						"0.12": [0, 0, 0],
						"0.24": [0, 0, 0],
						"0.44": [0, 0, 1],
						"0.52": [0, 0, 1],
						"0.68": [0, 0, 0]
					}
				},
				"RightArm": {
					"rotation": {
						"0.0": [26.15, -4.09, 3.77],
						"0.12": [47.06283, -7.35559, 6.79333],
						"0.24": [61.86144, -9.45147, 8.17103],
						"0.44": [-77.43098, 32.32189, -4.60921],
						"0.52": [-74.83368, 36.57898, -0.21535],
						"0.68": [0, 0, 0]
					},
					"position": {
						"0.0": [0, 0, 0.55],
						"0.12": [0, 0, 1],
						"0.24": [0, 0, 1],
						"0.44": [0, -1, -3.55],
						"0.52": [0, -1, -3.55],
						"0.68": [0, 0, 0]
					}
				},
				"LeftLeg": {
					"rotation": {
						"0.0": [-4.17, 0, 0],
						"0.12": [-7.5, 0, 0],
						"0.24": [-7.61435, -9.91358, 1.31845],
						"0.44": [-2.06754, 22.40972, -5.40961],
						"0.52": [-4.56754, 22.40972, -5.40961],
						"0.68": [0, 0, 0]
					},
					"position": {
						"0.0": [0, 0, 0],
						"0.12": [0, 0, 0],
						"0.24": [0, 0, 0],
						"0.44": [2, 0, -1],
						"0.52": [2, 0, -1],
						"0.68": [0, 0, 0]
					}
				},
				"RightLeg": {
					"rotation": {
						"0.0": [13.89, 0, 0],
						"0.12": [25, 0, 0],
						"0.24": [30, 0, 0],
						"0.44": [-28.77291, 28.57693, 8.66044],
						"0.52": [-23.77291, 28.57693, 8.66044],
						"0.68": [0, 0, 0]
					},
					"position": {
						"0.0": [0, 0, 0],
						"0.12": [0, 0, 0],
						"0.24": [0, 0, 0],
						"0.44": [0, 0, -1],
						"0.52": [0, 0, -1],
						"0.68": [0, 0, 0]
					}
				},
				"RightItem": {
					"rotation": {
						"0.0": [-26.57, 0.67, -0.13],
						"0.12": [-47.82387, 1.20345, -0.23574],
						"0.24": [-47.82387, 1.20345, -0.23574],
						"0.44": [52.17613, 1.20345, -0.23574],
						"0.52": [52.17613, 1.20345, -0.23574],
						"0.68": [0, 0, 0]
					},
					"position": {
						"0.0": [0, -1.67, 2.22],
						"0.12": [0, -3, 4],
						"0.24": [0, -3, 4],
						"0.32": [0, 0, -0.5],
						"0.44": [0, -3, -5],
						"0.52": [0, -3, -5],
						"0.68": [0, 0, 0]
					}
				}
			}
		},
		"hammer_axe_1": {
			"loop": "hold_on_last_frame",
			"animation_length": 0.88,
			"bones": {
				"Body": {
					"rotation": {
						"0.0": [0, 0, 0],
						"0.28": [-17.5, 0, 0],
						"0.4": [-17.5, 0, 0],
						"0.6": [47.5, 0, 0]
					},
					"position": {
						"0.0": [0, 0, 0],
						"0.28": [0, -0.5, 2],
						"0.4": [0, -0.5, 2],
						"0.48": [0, -1, -3.5],
						"0.6": [0, -3.5, -8]
					}
				},
				"Head": {
					"rotation": {
						"0.0": [0, 0, 0],
						"0.08": [-5, 0, 0],
						"0.4": [-18.93, 0, 0],
						"0.6": [-25, 0, 0]
					},
					"position": {
						"0.0": [0, 0, 0],
						"0.28": [0, 0.5, 1.5],
						"0.4": [0, 0.5, 1.5],
						"0.6": [0, 0, 0]
					}
				},
				"LeftArm": {
					"rotation": {
						"0.0": [0, 0, 0],
						"0.08": [-74.08781, 38.21793, 7.28615],
						"0.28": [-192.74765, 15.7627, -37.15736],
						"0.4": [-194.06837, 14.60251, -42.197],
						"0.6": [-41.9099, 42.22796, 2.52423]
					},
					"position": {
						"0.0": [0, 0, 0],
						"0.28": [-5, 1, -4],
						"0.4": [-5.5, 1.75, -4],
						"0.6": [-2, -2, -3]
					}
				},
				"RightArm": {
					"rotation": {
						"0.0": [0, 0, 0],
						"0.08": [-99.41958, -19.04355, 10.21668],
						"0.28": [-172.5, 0, 0],
						"0.4": [-177.5, 0, 0],
						"0.6": [-52.87531, -30.38608, -12.86613]
					},
					"position": {
						"0.0": [0, 0, 0],
						"0.28": [0, 3, -1],
						"0.4": [0, 3, -1],
						"0.6": [0, -1, -2]
					}
				},
				"LeftLeg": {
					"rotation": {
						"0.0": [0, 0, 0],
						"0.28": [20.60781, -7.62163, -1.15582],
						"0.4": [20.60781, -7.62163, -1.15582],
						"0.6": [-34.39219, -7.62163, -1.15582]
					},
					"position": {
						"0.0": [0, 0, 0],
						"0.28": [1, 0, 1],
						"0.4": [1, 0, 1],
						"0.6": [1, 0, -1]
					}
				},
				"RightLeg": {
					"rotation": {
						"0.0": [0, 0, 0],
						"0.28": [15.51711, -7.7474, -0.0905],
						"0.4": [15.51711, -7.7474, -0.0905],
						"0.6": [-56.98289, -7.7474, -0.0905]
					},
					"position": {
						"0.0": [0, 0, 0],
						"0.28": [0, -0.5, 0.5],
						"0.4": [0, -0.5, 0.5],
						"0.48": [0, 0.25, -0.75],
						"0.6": [0, 0, -1]
					}
				}
			}
		},
		"hammer_axe_2": {
			"loop": "hold_on_last_frame",
			"animation_length": 0.88,
			"bones": {
				"Body": {
					"rotation": {
						"0.0": [47.5, 0, 0],
						"0.28": [2.68789, -27.48982, -0.48922],
						"0.36": [2.91033, -34.98091, -0.91727],
						"0.56": [3.52563, 47.43028, 3.35016]
					},
					"position": {
						"0.0": [0, -3.5, -8],
						"0.28": [0, 0, 1],
						"0.36": [0, 0, 1],
						"0.56": [1.5, 0, -1]
					}
				},
				"Head": {
					"rotation": {
						"0.0": [-25, 0, 0],
						"0.28": [0, 0, 0],
						"0.36": [0, -15, 0],
						"0.56": [-7.5, 2.5, 0]
					},
					"position": {
						"0.0": [0, 0, 0],
						"0.28": [0, 0, 0],
						"0.36": [0, 0, 0]
					}
				},
				"LeftArm": {
					"rotation": {
						"0.0": [-41.9099, 42.22796, 2.52423],
						"0.28": [-49.83108, 14.71489, 10.41995],
						"0.36": [-54.83108, 14.71489, 10.41995],
						"0.56": [36.94161, 29.36109, 122.16017]
					},
					"position": {
						"0.0": [-2, -2, -3],
						"0.28": [1, -4, 3],
						"0.36": [1, -4, 3],
						"0.56": [-6, -4, -1]
					}
				},
				"RightArm": {
					"rotation": {
						"0.0": [-52.87531, -30.38608, -12.86613],
						"0.28": [-158.21501, -50.54809, 109.83813],
						"0.36": [-163.21501, -50.54809, 109.83813],
						"0.52": [-8.68, -14.49, 101.92],
						"0.56": [113.55186, 67.25816, 216.82896]
					},
					"position": {
						"0.0": [0, -1, -2],
						"0.28": [4, -1, -2],
						"0.36": [4, -1, -2],
						"0.56": [2, -1, 1]
					}
				},
				"LeftLeg": {
					"rotation": {
						"0.0": [-34.39219, -7.62163, -1.15582],
						"0.04": [-29.21549, -1.41662, -8.14528],
						"0.12": [-20.83426, 6.72021, -12.10317],
						"0.16": [-16.62828, 11.5452, -12.59668],
						"0.24": [-6.7, 23.31, -6.23],
						"0.28": [-3.67223, 27.77567, -3.14662],
						"0.36": [15.6529, 20.0088, -1.78767],
						"0.56": [-75.7966, -11.05866, 3.64814]
					},
					"position": {
						"0.0": [1, 0, -1],
						"0.12": [1.43, 0.64, -0.57],
						"0.28": [2, -0.25, 0],
						"0.36": [2, -0.25, 0],
						"0.56": [1, 0, 1]
					}
				},
				"RightLeg": {
					"rotation": {
						"0.0": [-56.98289, -7.7474, -0.0905],
						"0.08": [-41.11798, 0.88826, -0.36038],
						"0.16": [-31.49648, 11.65847, -1.95433],
						"0.24": [-16.38814, 18.15958, -0.90015],
						"0.28": [-10.20569, 22.47741, -1.03509],
						"0.36": [-5.20569, 22.47741, -1.03509],
						"0.56": [-12.33581, -32.73032, 0.90553]
					},
					"position": {
						"0.0": [0, 0, -1],
						"0.08": [-1.29, 0.5, -1],
						"0.16": [-1.17, 0.8, -0.75],
						"0.28": [-1, 0, -1],
						"0.36": [-1, 0, -1],
						"0.56": [0, 0, -2]
					}
				}
			}
		},
		"hammer_axe_3": {
			"loop": true,
			"bones": {
				"Body": {
					"rotation": [3.52563, 47.43028, 3.35016],
					"position": [1.5, 0, -1]
				},
				"Head": {
					"rotation": [-7.5, 2.5, 0]
				},
				"LeftArm": {
					"rotation": [36.94161, 29.36109, 122.16017],
					"position": [-6, -4, -1]
				},
				"RightArm": {
					"rotation": [113.55186, 67.25816, 216.82896],
					"position": [2, -1, 1]
				},
				"LeftLeg": {
					"rotation": [-75.7966, -11.05866, 3.64814],
					"position": [1, 0, 1]
				},
				"RightLeg": {
					"rotation": [-12.33581, -32.73032, 0.90553],
					"position": [0, 0, -2]
				}
			}
		},
		"hammer_axe_use": {
			"loop": "hold_on_last_frame",
			"animation_length": 1,
			"bones": {
				"Head": {
					"rotation": {
						"0.0": [0, 0, 0],
						"0.16": [17.5, 0, 0],
						"0.44": [-30, 0, 0],
						"0.64": [37.5, 0, 0],
						"1.0": [0, 0, 0]
					},
					"position": {
						"0.0": [0, 0, 0],
						"1.0": [0, 0, 0]
					}
				},
				"Body": {
					"rotation": {
						"0.0": [0, 0, 0],
						"0.16": [7.5, 0, 0],
						"0.44": [-52.5, 12.5, 0],
						"0.64": [35, -27.5, 0],
						"1.0": [0, 0, 0]
					},
					"position": {
						"0.0": [0, 0, 0],
						"0.16": [0, -0.95, -2],
						"0.32": [0, -1.19, 5.43],
						"0.44": [2, -4, 10],
						"0.64": [2, -3, -5],
						"1.0": [0, 0, 0]
					}
				},
				"RightArm": {
					"rotation": {
						"0.0": [0, 0, 0],
						"0.16": [-20, -12.5, 0],
						"0.44": [-145, -12.5, 0],
						"0.64": [-35, -12.5, 0],
						"1.0": [0, 0, 0]
					},
					"position": {
						"0.0": [0, 0, 0],
						"1.0": [0, 0, 0]
					}
				},
				"LeftArm": {
					"rotation": {
						"0.0": [0, 0, 0],
						"0.08": [-30, 67.5, 7.5],
						"0.16": [-47.5, 59.17, 0],
						"0.32": [-105, 42.5, 0],
						"0.44": [-142.5, 67.5, 0],
						"0.64": [-47.5, 67.5, 0],
						"1.0": [0, 0, 0]
					},
					"position": {
						"0.0": [0, 0, 0],
						"0.08": [-2, -0.5, 0],
						"0.16": [-2, -1, 0],
						"1.0": [0, 0, 0]
					}
				},
				"RightLeg": {
					"rotation": {
						"0.0": [0, 0, 0],
						"0.16": [-25, 0, 0],
						"0.44": [17.5, 0, 0],
						"0.64": [-37.5, 0, 0],
						"1.0": [0, 0, 0]
					},
					"position": {
						"0.0": [0, 0, 0],
						"0.16": [0, 0, 0],
						"0.44": [0, 1, -2],
						"0.64": [0, 2.5, -2],
						"1.0": [0, 0, 0]
					}
				},
				"LeftLeg": {
					"rotation": {
						"0.0": [0, 0, 0],
						"0.16": [15, 0, 0],
						"0.44": [55, 0, 0],
						"0.64": [-20, 0, 0],
						"1.0": [0, 0, 0]
					},
					"position": {
						"0.0": [0, 0, 0],
						"0.16": [0, 0, 0],
						"0.44": [0, 1, 2],
						"0.64": [0, 0.64, 0.29],
						"1.0": [0, 0, 0]
					}
				}
			}
		},
		"dual_blades_1": {
			"loop": "hold_on_last_frame",
			"animation_length": 0.48,
			"bones": {
				"Body": {
					"rotation": {
						"0.0": [0, 0, 0],
						"0.08": [19.83662, -5, 0],
						"0.28": [1.41183, 0, 0]
					},
					"position": {
						"0.0": [0, 0, 0],
						"0.08": [0.5, -2, -3],
						"0.16": [0.7, -1.2, -2.2],
						"0.2": [0.8, -0.72, -0.47],
						"0.28": [1, -1.25, 3]
					}
				},
				"LeftArm": {
					"rotation": {
						"0.0": [0, 0, 0],
						"0.12": [-223.02225, -4.13678, 12.20275]
					},
					"position": {
						"0.0": [0, 0, 0],
						"0.08": [0, 0, 0],
						"0.28": [0, 0, 0]
					}
				},
				"RightArm": {
					"rotation": {
						"0.0": [0, 0, 0],
						"0.08": [-155.75486, -8.59477, 100.51318],
						"0.16": [-78.03447, -18.25274, 94.15956],
						"0.2": [-39.71517, -17.8735, 92.87632],
						"0.28": [37.076, 3.99396, 92.33381]
					},
					"position": {
						"0.0": [0, 0, 0],
						"0.08": [2.25, -1, -3],
						"0.28": [-0.75, -1, 1]
					}
				},
				"LeftLeg": {
					"rotation": {
						"0.0": [0, 0, 0],
						"0.08": [-34.82648, 0, 0],
						"0.16": [-0.13946, -6.16789, -9.10811],
						"0.28": [56.92345, -27.78131, -9.99988]
					},
					"position": {
						"0.0": [0, 0, 0],
						"0.08": [0, 0, 0],
						"0.16": [0.5, 0.5, -1],
						"0.2": [0.67, 0.42, -0.67],
						"0.28": [1, 1, 0]
					}
				},
				"RightLeg": {
					"rotation": {
						"0.0": [0, 0, 0],
						"0.08": [-17.5, 0, 0],
						"0.28": [-6.55667, -14.86235, -0.76396]
					},
					"position": {
						"0.0": [0, 0, 0],
						"0.08": [0, 0.75, 0],
						"0.28": [0, 1, -2]
					}
				}
			}
		},
		"dual_blades_2": {
			"loop": "hold_on_last_frame",
			"animation_length": 0.48,
			"bones": {
				"Body": {
					"rotation": {
						"0.0": [1.41183, 0, 0],
						"0.16": [14.5514, 16.95455, 2.41769]
					},
					"position": {
						"0.0": [1, -1.25, 3],
						"0.16": [0, -1.25, -2]
					}
				},
				"LeftArm": {
					"rotation": {
						"0.0": [-223.02225, -4.13678, 12.20275],
						"0.16": [-33.02225, -4.13678, 12.20275]
					},
					"position": {
						"0.0": [0, 0, 0],
						"0.16": [0, -3, -4]
					}
				},
				"RightArm": {
					"rotation": {
						"0.0": [37.076, 3.99396, 92.33381],
						"0.16": [23.72868, 2.79808, 83.57721]
					},
					"position": {
						"0.0": [-0.75, -1, 1],
						"0.16": [-0.75, -1, 1]
					}
				},
				"LeftLeg": {
					"rotation": {
						"0.0": [56.92345, -27.78131, -9.99988],
						"0.16": [-43.94916, -12.31873, 1.99687]
					},
					"position": {
						"0.0": [1, 1, 0],
						"0.16": [1, 0, -1]
					}
				},
				"RightLeg": {
					"rotation": {
						"0.0": [-6.55667, -14.86235, -0.76396],
						"0.16": [20.94333, -14.86235, -0.76396]
					},
					"position": {
						"0.0": [0, 1, -2],
						"0.16": [0, 1, 1]
					}
				}
			}
		},
		"dual_blades_3": {
			"loop": "hold_on_last_frame",
			"animation_length": 0.48,
			"bones": {
				"Body": {
					"rotation": {
						"0.0": [14.5514, 16.95455, 2.41769],
						"0.08": [15.59323, 5.544, -3.61922],
						"0.12": [15.59323, 5.544, -3.61922],
						"0.24": [8.70096, -31.64234, -3.36362]
					},
					"position": {
						"0.0": [0, -1.25, -2],
						"0.24": [1, -0.75, -3.48]
					}
				},
				"LeftArm": {
					"rotation": {
						"0.0": [-33.02225, -4.13678, 12.20275],
						"0.24": [-46.69351, -32.67402, 14.9531]
					},
					"position": {
						"0.0": [0, -3, -4],
						"0.24": [0, -1, 1]
					}
				},
				"RightArm": {
					"rotation": {
						"0.0": [23.72868, 2.79808, 83.57721],
						"0.04": [20.81916, 6.79537, 29.53726],
						"0.08": [26.28917, -9.72655, 15.73749],
						"0.24": [-54.42265, 29.25458, -3.22251]
					},
					"position": {
						"0.0": [-0.75, -1, 1],
						"0.08": [-0.54, -1, 0.86],
						"0.24": [0, -2, -4]
					}
				},
				"RightItem": {
					"rotation": {
						"0.0": [0, 0, 0],
						"0.08": [-37.5, 0, 0],
						"0.12": [-27.5, 0, 0],
						"0.24": [35, 0, 0]
					},
					"position": {
						"0.0": [0, 0, 0],
						"0.08": [0, -1.6, 2.9],
						"0.12": [0, -1.6, 2.9],
						"0.24": [0, -1.5, -2.75]
					}
				},
				"LeftLeg": {
					"rotation": {
						"0.0": [-43.94916, -12.31873, 1.99687],
						"0.24": [9.09273, 12.49933, 1.16607]
					},
					"position": {
						"0.0": [1, 0, -1],
						"0.24": [2, 0, -2]
					}
				},
				"RightLeg": {
					"rotation": {
						"0.0": [20.94333, -14.86235, -0.76396],
						"0.08": [7.13534, -16.80024, 4.02733],
						"0.12": [7.13534, -16.80024, 4.02733],
						"0.24": [-24.48911, 18.78554, 3.05174]
					},
					"position": {
						"0.0": [0, 1, 1],
						"0.08": [0, 1, 1],
						"0.12": [0, 1, 1],
						"0.16": [0, 1.4, 0.4],
						"0.24": [-1, 0, 0]
					}
				}
			}
		},
		"dual_blades_4": {
			"loop": "hold_on_last_frame",
			"animation_length": 0.48,
			"bones": {
				"Body": {
					"rotation": {
						"0.0": [8.70096, -31.64234, -3.36362],
						"0.08": [-4.40677, 5.544, -3.61922],
						"0.24": [28.60817, -41.11251, -7.46724]
					},
					"position": {
						"0.0": [1, -0.75, -3.48],
						"0.08": [1, -0.75, 1.52],
						"0.24": [1, -1.5, -8.23]
					}
				},
				"LeftArm": {
					"rotation": {
						"0.0": [-46.69351, -32.67402, 14.9531],
						"0.24": [-46.69351, -32.67402, 14.9531]
					},
					"position": {
						"0.0": [0, -1, 1],
						"0.24": [0, -1, 1]
					}
				},
				"RightArm": {
					"rotation": {
						"0.0": [-54.42265, 29.25458, -3.22251],
						"0.08": [36.28917, -9.72655, 15.73749],
						"0.24": [-75.58201, 33.13403, -7.87212]
					},
					"position": {
						"0.0": [0, -2, -4],
						"0.08": [-0.54, -1, 0.86],
						"0.24": [0, -1, -5]
					}
				},
				"RightItem": {
					"rotation": {
						"0.0": [35, 0, 0],
						"0.08": [-25, 0, 0],
						"0.24": [52.5, 0, 0]
					},
					"position": {
						"0.0": [0, -1.5, -2.75],
						"0.08": [0, -1.6, 2.9],
						"0.24": [0, -4.5, -5.75]
					}
				},
				"LeftLeg": {
					"rotation": {
						"0.0": [9.09273, 12.49933, 1.16607],
						"0.08": [-1.93841, -7.37556, -0.65055],
						"0.24": [-9.63632, 26.63672, -15.26234]
					},
					"position": {
						"0.0": [2, 0, -2],
						"0.24": [2, 0, -2]
					}
				},
				"RightLeg": {
					"rotation": {
						"0.0": [-24.48911, 18.78554, 3.05174],
						"0.08": [14.63534, -16.80024, 4.02733],
						"0.24": [-37.89821, 28.91462, -1.90313]
					},
					"position": {
						"0.0": [-1, 0, 0],
						"0.08": [0, 1, 1],
						"0.24": [0, 1, -0.5]
					}
				}
			}
		},
		"dual_blades_5": {
			"loop": "hold_on_last_frame",
			"animation_length": 0.48,
			"bones": {
				"Body": {
					"rotation": {
						"0.0": [28.60817, -41.11251, -7.46724],
						"0.08": [16.39021, -31.57133, -3.7383],
						"0.2": [0, 0, 0],
						"0.32": [0, 180, 0],
						"0.48": [0, 365, 0]
					},
					"position": {
						"0.0": [1, -1.5, -8.23],
						"0.08": [1, -1.5, -5.73],
						"0.12": [1, -0.83, -4.06],
						"0.16": [1, -0.16, -2.39],
						"0.2": [1, 0.5, 1.27],
						"0.24": [4, 0.5, 1.27],
						"0.32": [5, 0.5, -1.73],
						"0.4": [3, 0.5, -2.23],
						"0.48": [1, 0.5, 1.27]
					}
				},
				"LeftArm": {
					"rotation": {
						"0.0": [-46.69351, -32.67402, 14.9531],
						"0.08": [-60.27812, -7.89042, 24.43974],
						"0.2": [-43.33842, -15.72959, 62.09478],
						"0.48": [-43.33842, -15.72959, 62.09478]
					},
					"position": {
						"0.0": [0, -1, 1],
						"0.2": [-4, 0, -4],
						"0.48": [-4, 0, -4]
					}
				},
				"LeftItem": {
					"rotation": {
						"0.0": [0, 0, 0],
						"0.08": [0, 0, 0],
						"0.2": [50, 0, 0],
						"0.48": [50, 0, 0]
					},
					"position": {
						"0.0": [0, 0, 0],
						"0.08": [0, 0, 0],
						"0.2": [0, -4, -6],
						"0.48": [0, -4, -6]
					}
				},
				"RightArm": {
					"rotation": {
						"0.0": [-75.58201, 33.13403, -7.87212],
						"0.08": [-75.31074, -3.53837, 57.31426],
						"0.2": [-70.8279, -6.54296, 67.51195],
						"0.48": [-70.8279, -6.54296, 67.51195]
					},
					"position": {
						"0.0": [0, -1, -5],
						"0.2": [0, -1, -3],
						"0.48": [0, -1, -3]
					}
				},
				"RightItem": {
					"rotation": {
						"0.0": [52.5, 0, 0],
						"0.04": [0, 0, 0],
						"0.08": [0, 0, 0],
						"0.2": [50, 0, 0],
						"0.48": [50, 0, 0]
					},
					"position": {
						"0.0": [0, -4.5, -5.75],
						"0.04": [0, 0, 0],
						"0.08": [0, 0, 0],
						"0.2": [0, -4, -6],
						"0.48": [0, -4, -6]
					}
				},
				"LeftLeg": {
					"rotation": {
						"0.0": [-9.63632, 26.63672, -15.26234],
						"0.08": [-5.11705, 13.57557, -3.23777],
						"0.2": [-5.12, 13.58, -3.24],
						"0.48": [-5.12, 13.58, -3.24]
					},
					"position": {
						"0.0": [2, 0, -2],
						"0.2": [0, 0, 0],
						"0.48": [0, 0, 0]
					}
				},
				"RightLeg": {
					"rotation": {
						"0.0": [-37.89821, 28.91462, -1.90313],
						"0.08": [-15.76802, 19.90915, -2.00417],
						"0.2": [-58.26802, 19.90915, -2.00417],
						"0.48": [-58.27, 19.91, -2]
					},
					"position": {
						"0.0": [0, 1, -0.5],
						"0.2": [0, 0, 0],
						"0.48": [0, 0, 0]
					}
				}
			}
		},
		"dual_blades_6": {
			"loop": "hold_on_last_frame",
			"animation_length": 0.48,
			"bones": {
				"Body": {
					"rotation": {
						"0.0": [0, 5, 0],
						"0.12": [0, -17.5, 0],
						"0.28": [0, 180, 0],
						"0.44": [0, 365, 0]
					},
					"position": {
						"0.0": [1, 0.5, 1.27],
						"0.12": [1, 0.5, 1.27],
						"0.2": [4, 0.5, 1.27],
						"0.28": [5, 0.5, -1.73],
						"0.36": [3, 0.5, -2.23],
						"0.44": [1, 0.5, 1.27]
					}
				},
				"LeftArm": {
					"rotation": {
						"0.0": [-43.33842, -15.72959, 62.09478],
						"0.12": [-158.76411, -5.1178, 92.28375],
						"0.44": [-158.76411, -5.1178, 92.28375]
					},
					"position": {
						"0.0": [-4, 0, -4],
						"0.12": [1, 0, -2],
						"0.44": [1, 0, -2]
					}
				},
				"LeftItem": {
					"rotation": {
						"0.0": [50, 0, 0],
						"0.12": [50, 0, 0],
						"0.44": [50, 0, 0]
					},
					"position": {
						"0.0": [0, -4, -6],
						"0.12": [0, -4, -6],
						"0.44": [0, -4, -6]
					}
				},
				"RightArm": {
					"rotation": {
						"0.0": [-70.8279, -6.54296, 67.51195],
						"0.12": [-15.8279, -6.54296, 67.51195],
						"0.44": [-15.8279, -6.54296, 67.51195]
					},
					"position": {
						"0.0": [0, -1, -3],
						"0.12": [0, -1, -3],
						"0.44": [0, -1, -3]
					}
				},
				"RightItem": {
					"rotation": {
						"0.0": [50, 0, 0],
						"0.12": [50, 0, 0],
						"0.44": [50, 0, 0]
					},
					"position": {
						"0.0": [0, -4, -6],
						"0.12": [0, -4, -6],
						"0.44": [0, -4, -6]
					}
				},
				"LeftLeg": {
					"rotation": {
						"0.0": [-5.12, 13.58, -3.24],
						"0.12": [-5.12, 13.58, -3.24],
						"0.44": [-5.12, 13.58, -3.24]
					},
					"position": {
						"0.0": [0, 0, 0],
						"0.12": [0, 0, 0],
						"0.44": [0, 0, 0]
					}
				},
				"RightLeg": {
					"rotation": {
						"0.0": [-58.27, 19.91, -2],
						"0.12": [-33.50441, -9.36834, 0.22617],
						"0.44": [-58.27, 19.91, -2]
					},
					"position": {
						"0.0": [0, 0, 0],
						"0.12": [0, 0, 0],
						"0.44": [0, 0, 0]
					}
				}
			}
		},
		"dual_blades_7": {
			"loop": "hold_on_last_frame",
			"animation_length": 0.48,
			"bones": {
				"Body": {
					"rotation": {
						"0.0": [0, 5, 0],
						"0.08": [32.5, 0, 0],
						"0.12": [32.5, 0, 0],
						"0.4": [30, 0, 0]
					},
					"position": {
						"0.0": [1, 0.5, 1.27],
						"0.08": [0, -4.5, -3],
						"0.12": [0, -5.5, -3],
						"0.2": [0, -0.5, -5],
						"0.28": [0, -0.5, -5],
						"0.4": [0, -2.5, -5]
					}
				},
				"LeftArm": {
					"rotation": {
						"0.0": [-158.76411, -5.1178, 92.28375],
						"0.08": [-65.70681, 49.6362, -40.46992],
						"0.2": [-91.40821, 33.31066, -48.98289],
						"0.28": [-91.40821, 33.31066, -48.98289],
						"0.4": [18.09244, 14.44082, -56.2847]
					},
					"position": {
						"0.0": [1, 0, -2],
						"0.08": [0, 0, 0],
						"0.4": [0, 0, -2]
					}
				},
				"LeftItem": {
					"rotation": {
						"0.0": [50, 0, 0],
						"0.08": [0, 0, 0],
						"0.4": [0, 0, 0]
					},
					"position": {
						"0.0": [0, -4, -6],
						"0.08": [0, 0, 0],
						"0.4": [0, 0, 0]
					}
				},
				"RightArm": {
					"rotation": {
						"0.0": [-15.8279, -6.54296, 67.51195],
						"0.08": [-65.70681, -49.6362, 40.46992],
						"0.2": [-88.90821, -33.31066, 48.98289],
						"0.28": [-88.90821, -33.31066, 48.98289],
						"0.4": [18.09244, -14.44082, 56.2847]
					},
					"position": {
						"0.0": [0, -1, -3],
						"0.08": [0, 0, 0],
						"0.4": [0, 0, -2]
					}
				},
				"RightItem": {
					"rotation": {
						"0.0": [50, 0, 0],
						"0.08": [0, 0, 0],
						"0.4": [0, 0, 0]
					},
					"position": {
						"0.0": [0, -4, -6],
						"0.08": [0, 0, 0],
						"0.4": [0, 0, 0]
					}
				},
				"LeftLeg": {
					"rotation": {
						"0.0": [-5.12, 13.58, -3.24],
						"0.08": [-37.5, 0, 0],
						"0.12": [-37.5, 0, 0],
						"0.2": [-19.8423, -2.55868, -7.05239],
						"0.28": [-19.8423, -2.55868, -7.05239],
						"0.4": [-54.84, -2.56, -7.05]
					},
					"position": {
						"0.0": [0, 0, 0],
						"0.08": [0, 3, -1],
						"0.12": [0, 3, -1],
						"0.2": [0, 4, -3],
						"0.28": [0, 4, -3],
						"0.4": [0, 0, 0]
					}
				},
				"RightLeg": {
					"rotation": {
						"0.0": [-58.27, 19.91, -2],
						"0.08": [-37.5, 0, 0],
						"0.12": [-37.5, 0, 0],
						"0.2": [-19.8423, 2.55868, 7.05239],
						"0.28": [-19.8423, 2.55868, 7.05239],
						"0.4": [-2.34, 2.56, 7.05]
					},
					"position": {
						"0.0": [0, 0, 0],
						"0.08": [0, 3, -2],
						"0.12": [0, 3, -2],
						"0.2": [0, 4, -3],
						"0.28": [0, 4, -3],
						"0.4": [0, 0, 0]
					}
				}
			}
		},
		"dual_blades_8": {
			"loop": true,
			"bones": {
				"Body": {
					"rotation": [30, 0, 0],
					"position": [0, -2.5, -5]
				},
				"LeftArm": {
					"rotation": [18.09244, 14.44082, -56.2847],
					"position": [0, 0, -2]
				},
				"LeftItem": {
					"rotation": [0, 0, 0],
					"position": [0, 0, 0]
				},
				"RightArm": {
					"rotation": [18.09244, -14.44082, 56.2847],
					"position": [0, 0, -2]
				},
				"RightItem": {
					"rotation": [0, 0, 0],
					"position": [0, 0, 0]
				},
				"LeftLeg": {
					"rotation": [-54.84, -2.56, -7.05],
					"position": [0, 0, 0]
				},
				"RightLeg": {
					"rotation": [-2.34, 2.56, 7.05],
					"position": [0, 0, 0]
				}
			}
		},
		"dual_blades_use": {
			"animation_length": 0.76,
			"bones": {
				"Body": {
					"rotation": {
						"0.0": [0, 0, 0],
						"0.08": [15, 0, 0],
						"0.16": [25, 0, 0],
						"0.24": [15, 0, 0],
						"0.36": [-90, 0, 0],
						"0.48": [-180, 0, 0],
						"0.6": [-270, 0, 0],
						"0.76": [-360, 0, 0]
					},
					"position": {
						"0.0": [0, 0, 0],
						"0.08": [0, -1.5, -2.9],
						"0.16": [0, -2.5, -4.65],
						"0.24": [0, -1.5, -2.9],
						"0.36": [0, 0, 4],
						"0.6": [0, 0, 4],
						"0.76": [0, 0, 0]
					}
				},
				"Head": {
					"rotation": {
						"0.0": [0, 0, 0],
						"0.08": [12.5, 0, 0],
						"0.16": [12.5, 0, 0],
						"0.24": [12.5, 0, 0],
						"0.36": [42.5, 0, 0],
						"0.6": [42.5, 0, 0],
						"0.76": [0, 0, 0]
					},
					"position": {
						"0.0": [0, 0, 0],
						"0.76": [0, 0, 0]
					}
				},
				"LeftArm": {
					"rotation": {
						"0.0": [0, 0, 0],
						"0.08": [-17.5, 0, 0],
						"0.16": [-17.5, 0, 0],
						"0.24": [-17.5, 0, 0],
						"0.32": [17.5, 0, 0],
						"0.36": [-25, 0, 0],
						"0.6": [-47.5, 0, 0],
						"0.76": [0, 0, 0]
					},
					"position": {
						"0.0": [0, 0, 0],
						"0.76": [0, 0, 0]
					}
				},
				"RightArm": {
					"rotation": {
						"0.0": [0, 0, 0],
						"0.08": [-17.5, 0, 0],
						"0.16": [-17.5, 0, 0],
						"0.24": [-17.5, 0, 0],
						"0.32": [17.5, 0, 0],
						"0.36": [-25, 0, 0],
						"0.6": [-42.5, 0, 0],
						"0.76": [0, 0, 0]
					},
					"position": {
						"0.0": [0, 0, 0],
						"0.76": [0, 0, 0]
					}
				},
				"LeftLeg": {
					"rotation": {
						"0.0": [0, 0, 0],
						"0.08": [-15, 0, 0],
						"0.16": [-25, 0, 0],
						"0.24": [-15, 0, 0],
						"0.32": [-21.25, 0, 0],
						"0.36": [-67.5, 0, 0],
						"0.6": [-67.5, 0, 0],
						"0.76": [0, 0, 0]
					},
					"position": {
						"0.0": [0, 0, 0],
						"0.08": [0, 1, 0],
						"0.16": [0, 1, 0],
						"0.24": [0, 1, 0],
						"0.36": [0, 0, 0],
						"0.6": [0, 0, 0],
						"0.76": [0, 0, 0]
					}
				},
				"RightLeg": {
					"rotation": {
						"0.0": [0, 0, 0],
						"0.08": [-15, 0, 0],
						"0.16": [-25, 0, 0],
						"0.24": [-15, 0, 0],
						"0.32": [-21.25, 0, 0],
						"0.36": [-67.5, 0, 0],
						"0.6": [-67.5, 0, 0],
						"0.76": [0, 0, 0]
					},
					"position": {
						"0.0": [0, 0, 0],
						"0.08": [0, 1, 0],
						"0.16": [0, 1, 0],
						"0.24": [0, 1, 0],
						"0.36": [0, 0, 0],
						"0.6": [0, 0, 0],
						"0.76": [0, 0, 0]
					}
				}
			}
		},
		"glove_1": {
			"loop": "hold_on_last_frame",
			"animation_length": 0.48,
			"bones": {
				"Body": {
					"rotation": {
						"0.0": [0, 0, 0],
						"0.12": [-5, -10, 0],
						"0.24": [5.08082, 2.4529, -0.64584],
						"0.28": [19.33239, 23.88885, 6.07118]
					},
					"position": {
						"0.0": [0, 0, 0],
						"0.12": [0, 0, 1],
						"0.2": [0, -1.2, -0.4],
						"0.24": [0, -0.8, -2.6],
						"0.28": [0, -1, -3]
					}
				},
				"LeftArm": {
					"rotation": {
						"0.0": [0, 0, 0],
						"0.12": [-65, 0, 0],
						"0.24": [-63.00444, -0.04861, 0.70329],
						"0.28": [-104.00884, -19.98865, -3.38224]
					},
					"position": {
						"0.0": [0, 0, 0],
						"0.12": [0, 0, 4],
						"0.24": [-1.5, 0.25, -2],
						"0.28": [-2, 1, -4]
					}
				},
				"RightArm": {
					"rotation": {
						"0.0": [0, 0, 0],
						"0.12": [-17.5, 0, 0],
						"0.28": [-23.85011, 14.50601, 21.85297]
					},
					"position": [0, 0, 0]
				},
				"LeftLeg": {
					"rotation": {
						"0.0": [0, 0, 0],
						"0.12": [17.5, 0, 0],
						"0.24": [-7.5, 0, 0],
						"0.28": [-33.00087, -18.01405, -1.37554]
					},
					"position": {
						"0.0": [0, 0, 0],
						"0.24": [0, 1, -1],
						"0.28": [0, 1, -2]
					}
				},
				"RightLeg": {
					"rotation": {
						"0.0": [0, 0, 0],
						"0.12": [5, 0, 0],
						"0.24": [10, 0, 0],
						"0.28": [-1.46217, -13.5323, 5.38726]
					},
					"position": {
						"0.0": [0, 0, 0],
						"0.24": [-1.5, 0, 0],
						"0.28": [-2, 0, 0]
					}
				}
			}
		},
		"glove_2": {
			"loop": "hold_on_last_frame",
			"animation_length": 0.48,
			"bones": {
				"Body": {
					"rotation": {
						"0.0": [19.33239, 23.88885, 6.07118],
						"0.08": [18.68958, 19.16118, 4.32081],
						"0.2": [18.65777, -18.88823, -8.25304],
						"0.28": [37.80765, -55.25714, -30.17293]
					},
					"position": {
						"0.0": [0, -1, -3],
						"0.08": [0, -1, -3],
						"0.2": [0, -1, -3],
						"0.28": [0, -1, -3]
					}
				},
				"LeftArm": {
					"rotation": {
						"0.0": [-104.00884, -19.98865, -3.38224],
						"0.08": [-96.50884, -19.98865, -3.38224],
						"0.2": [-67.9984, 0.80284, 5.39281],
						"0.28": [-22.8954, 30.71427, 27.14118]
					},
					"position": {
						"0.0": [-2, 1, -4],
						"0.08": [-2, -1, -4],
						"0.2": [-2, -1, -1],
						"0.28": [-2, -1, -1]
					}
				},
				"RightArm": {
					"rotation": {
						"0.0": [-23.85011, 14.50601, 21.85297],
						"0.08": [-78.78805, -8.13319, 7.23936],
						"0.2": [-86.21012, 19.61039, 1.48724],
						"0.28": [-96.93187, -41.9134, 11.53965]
					},
					"position": {
						"0.0": [0, 0, 0],
						"0.08": [0, 0, 2],
						"0.2": [0, 0, -4],
						"0.28": [-1, 1, -2]
					}
				},
				"LeftLeg": {
					"rotation": {
						"0.0": [-33.00087, -18.01405, -1.37554],
						"0.08": [-13.00087, -18.01405, -1.37554],
						"0.2": [-3.68195, 19.06493, 0.56585],
						"0.28": [-17.05993, 57.42345, -6.50966]
					},
					"position": {
						"0.0": [0, 1, -2],
						"0.08": [0, 1, -2],
						"0.2": [1, 0, 0],
						"0.28": [0, 0, -2]
					}
				},
				"RightLeg": {
					"rotation": {
						"0.0": [-1.46217, -13.5323, 5.38726],
						"0.08": [-16.46217, -13.5323, 5.38726],
						"0.2": [-45.39679, 12.93603, 3.74109],
						"0.28": [-31.7001, 51.47811, 0.65531]
					},
					"position": {
						"0.0": [-2, 0, 0],
						"0.08": [-2, 2, 0],
						"0.28": [-2, 0, 1]
					}
				}
			}
		},
		"glove_3": {
			"loop": "hold_on_last_frame",
			"animation_length": 0.48,
			"bones": {
				"Body": {
					"rotation": {
						"0.0": [37.80765, -55.25714, -30.17293],
						"0.08": [18.68958, -19.16118, -4.32081],
						"0.2": [18.65777, 18.88823, 8.25304],
						"0.28": [40.30765, 55.25714, 30.17293]
					},
					"position": {
						"0.0": [0, -1, -3],
						"0.08": [0, -1, -3],
						"0.2": [0, -1, -3],
						"0.28": [0, -1, -3]
					}
				},
				"LeftArm": {
					"rotation": {
						"0.0": [-22.8954, 30.71427, 27.14118],
						"0.08": [-78.78805, 8.13319, -7.23936],
						"0.2": [-86.21012, -19.61039, -1.48724],
						"0.28": [-99.43167, 56.76593, -14.80698]
					},
					"position": {
						"0.0": [-2, -1, -1],
						"0.08": [0, 0, 2],
						"0.2": [0, 0, -4],
						"0.28": [1, 1, -2]
					}
				},
				"RightArm": {
					"rotation": {
						"0.0": [-96.93187, -41.9134, 11.53965],
						"0.08": [-96.50884, 19.98865, 3.38224],
						"0.2": [-67.9984, -0.80284, -5.39281],
						"0.28": [-18.49676, -33.37012, -35.41941]
					},
					"position": {
						"0.0": [-1, 1, -2],
						"0.08": [2, -1, -4],
						"0.2": [2, -1, -1],
						"0.28": [2, -1, -1]
					}
				},
				"LeftLeg": {
					"rotation": {
						"0.0": [-10.91105, -33.43573, 14.05215],
						"0.08": [-16.46217, 13.5323, -5.38726],
						"0.2": [-45.39679, -12.93603, -3.74109],
						"0.28": [-38.70707, -58.32453, -7.5544]
					},
					"position": {
						"0.0": [0, 0, -2],
						"0.08": [2, 2, 0],
						"0.2": [1, 0, 0],
						"0.28": [2, 0, 1]
					}
				},
				"RightLeg": {
					"rotation": {
						"0.0": [-31.7001, 51.47811, 0.65531],
						"0.08": [-13.00087, 18.01405, 1.37554],
						"0.2": [-3.68195, -19.06493, -0.56585],
						"0.28": [-18.30488, -59.80552, 7.96765]
					},
					"position": {
						"0.0": [-2, 0, 1],
						"0.08": [0, 1, -2],
						"0.2": [-1, 0, 0],
						"0.28": [0, 0, -2]
					}
				}
			}
		},
		"glove_4": {
			"loop": "hold_on_last_frame",
			"animation_length": 0.6,
			"bones": {
				"Body": {
					"rotation": {
						"0.0": [40.30765, 55.25714, 30.17293],
						"0.04": [45, 0, 0],
						"0.12": [2.5, 0, 0],
						"0.24": [-12.14717, -43.90646, 10.99643],
						"0.32": [-27.37528, -66.00707, 20.87781],
						"0.36": [-27.37528, -66.00707, 20.87781],
						"0.44": [-27.37528, -66.00707, 20.87781],
						"0.48": [-9.45, -23.2, 7.71],
						"0.52": [0, 0, 0]
					},
					"position": {
						"0.0": [0, -1, -3],
						"0.04": [0, -4, -5],
						"0.12": [0, 3, 1],
						"0.24": [0, 0, 5],
						"0.32": [0, -2, 2.8],
						"0.36": [0, -5, 1],
						"0.4": [0, -6.67, 0],
						"0.44": [0, -6, 1],
						"0.48": [0, -0.8, 2],
						"0.52": [0, 0, 0]
					}
				},
				"Head": {
					"rotation": {
						"0.12": [0, 0, 0],
						"0.32": [0, 17.5, 0],
						"0.36": [0, 17.5, 0],
						"0.44": [0, 17.5, 0],
						"0.52": [0, 0, 0]
					}
				},
				"LeftArm": {
					"rotation": {
						"0.0": [-99.43167, 56.76593, -14.80698],
						"0.04": [-35, 0, -27.5],
						"0.12": [-9.85108, -1.72794, -37.35108],
						"0.24": [2.64892, -1.72794, -37.35108],
						"0.32": [2.11169, -2.35451, -22.35452],
						"0.36": [2.11169, -2.35451, -22.35452],
						"0.44": [2.11169, -2.35451, -22.35452],
						"0.48": [0.84, -0.94, -8.94],
						"0.52": [0, 0, 0]
					},
					"position": {
						"0.0": [1, 1, -2],
						"0.04": [0, 0, 0],
						"0.32": [0, 1, 0],
						"0.36": [0, 1, 0],
						"0.44": [0, 1, 0],
						"0.48": [0, 0, 0],
						"0.52": [0, 0, 0]
					}
				},
				"RightArm": {
					"rotation": {
						"0.0": [-18.49676, -33.37012, -35.41941],
						"0.04": [-35, 0, 27.5],
						"0.12": [-9.85108, 1.72794, 37.35108],
						"0.24": [2.53729, -0.86717, 22.57558],
						"0.32": [2.66473, -0.29766, 10.08787],
						"0.36": [2.66473, -0.29766, 10.08787],
						"0.44": [2.66473, -0.29766, 10.08787],
						"0.48": [1.07, -0.12, 4.04],
						"0.52": [0, 0, 0]
					},
					"position": {
						"0.0": [2, -1, -1],
						"0.04": [0, 0, 0],
						"0.32": [0, 1, 0],
						"0.36": [0, 1, 0],
						"0.44": [0, 1, 0],
						"0.48": [0, 0, 0],
						"0.52": [0, 0, 0]
					}
				},
				"LeftLeg": {
					"rotation": {
						"0.0": [-38.70707, -58.32453, -7.5544],
						"0.04": [-50, 0, 0],
						"0.12": [-4.81594, -2.15393, -9.76758],
						"0.24": [-1.52132, -30.97852, -25.68595],
						"0.32": [-14.33231, -17.1202, -22.79236],
						"0.36": [-14.33231, -17.1202, -22.79236],
						"0.44": [-14.33231, -17.1202, -22.79236],
						"0.48": [-22.61, -12.39, -10.27],
						"0.52": [0, 0, 0]
					},
					"position": {
						"0.0": [2, 0, 1],
						"0.04": [0, 2, -2],
						"0.12": [0, 0, -0.33],
						"0.32": [0, 4, -1],
						"0.36": [0, 5, -1],
						"0.44": [0, 5, -1],
						"0.48": [0, 0.4, 0],
						"0.52": [0, 0, 0]
					}
				},
				"RightLeg": {
					"rotation": {
						"0.0": [-18.30488, -59.80552, 7.96765],
						"0.04": [-47.5, 0, 0],
						"0.12": [-4.81594, 2.15393, 9.76758],
						"0.24": [-55.03213, 27.8681, -0.43144],
						"0.32": [-26.54818, 53.95352, 18.76647],
						"0.36": [-26.54818, 53.95352, 18.76647],
						"0.44": [-26.54818, 53.95352, 18.76647],
						"0.48": [-8.21, 14.67, 4.64],
						"0.52": [0, 0, 0]
					},
					"position": {
						"0.0": [0, 0, -2],
						"0.04": [0, 2, -2],
						"0.12": [-0.67, -0.1, -0.76],
						"0.24": [-1.56, -0.56, -1.44],
						"0.32": [-1.85, -0.45, 0],
						"0.36": [-0.85, -0.45, 0],
						"0.44": [-0.85, -0.45, 0],
						"0.48": [-0.8, 0, 0],
						"0.52": [0, 0, 0]
					}
				}
			}
		},
		"glove_5": {
			"animation_length": 0.12,
			"bones": {
				"Body": {
					"rotation": {
						"0.0": [-9.45, -23.2, 7.71],
						"0.08": [0, 0, 0]
					},
					"position": {
						"0.0": [0, -0.8, 2],
						"0.08": [0, 0, 0]
					}
				},
				"LeftArm": {
					"rotation": {
						"0.0": [0.84, -0.94, -8.94],
						"0.08": [0, 0, 0]
					},
					"position": {
						"0.0": [0, 0, 0],
						"0.08": [0, 0, 0]
					}
				},
				"RightArm": {
					"rotation": {
						"0.0": [1.07, -0.12, 4.04],
						"0.08": [0, 0, 0]
					},
					"position": {
						"0.0": [0, 0, 0],
						"0.08": [0, 0, 0]
					}
				},
				"LeftLeg": {
					"rotation": {
						"0.0": [-22.61, -12.39, -10.27],
						"0.08": [0, 0, 0]
					},
					"position": {
						"0.0": [0, 0.4, 0],
						"0.08": [0, 0, 0]
					}
				},
				"RightLeg": {
					"rotation": {
						"0.0": [-8.21, 14.67, 4.64],
						"0.08": [0, 0, 0]
					},
					"position": {
						"0.0": [-0.8, 0, 0],
						"0.08": [0, 0, 0]
					}
				}
			}
		},
		"glove_use": {
			"animation_length": 1.36,
			"bones": {
				"Body": {
					"rotation": {
						"0.0": [0, 0, 0],
						"0.08": [-15, 0, 0],
						"0.24": [90, 0, 0],
						"0.32": [180, 0, 0],
						"0.4": [270, 0, 0],
						"0.48": [360, 0, 0],
						"0.56": [450, 0, 0],
						"0.64": [540, 0, 0],
						"0.72": [630, 0, 0],
						"0.8": [720, 0, 0],
						"0.88": [810, 0, 0],
						"0.96": [900, 0, 0],
						"1.04": [990, 0, 0],
						"1.12": [1080, 0, 0],
						"1.24": [1072.5, 0, 0],
						"1.36": [1080, 0, 0]
					},
					"position": {
						"0.0": [0, 0, 0],
						"0.08": [0, -1.5, 2.9],
						"0.24": [0, -13.5, -1.7],
						"0.32": [0, -18.5, -1.7],
						"0.4": [0, -21.5, 6.3],
						"0.48": [0, -10.5, 3.3],
						"0.56": [0, -13.5, -1.7],
						"0.64": [0, -18.5, -1.7],
						"0.72": [0, -21.5, 6.3],
						"0.8": [0, -10.5, 3.3],
						"0.88": [0, -13.5, -1.7],
						"0.96": [0, -18.5, -1.7],
						"1.04": [0, -21.5, 6.3],
						"1.12": [0, -10.5, 3.3],
						"1.24": [0, -5.25, 1.65],
						"1.36": [0, 0, 0]
					}
				},
				"Head": {
					"rotation": {
						"0.0": [0, 0, 0],
						"0.08": [-12.5, 0, 0],
						"0.24": [62.5, 0, 0],
						"0.32": [62.5, 0, 0],
						"0.4": [62.5, 0, 0],
						"0.48": [62.5, 0, 0],
						"0.56": [62.5, 0, 0],
						"0.64": [62.5, 0, 0],
						"0.72": [62.5, 0, 0],
						"0.8": [62.5, 0, 0],
						"0.88": [62.5, 0, 0],
						"0.96": [62.5, 0, 0],
						"1.04": [62.5, 0, 0],
						"1.12": [62.5, 0, 0],
						"1.24": [31.25, 0, 0],
						"1.36": [0, 0, 0]
					},
					"position": {
						"0.0": [0, 0, 0],
						"0.24": [0, 0, 0],
						"0.56": [0, 0, 0],
						"1.24": [0, 0, 0],
						"1.36": [0, 0, 0]
					}
				},
				"LeftArm": {
					"rotation": {
						"0.0": [0, 0, 0],
						"0.08": [-237.5, 0, 0],
						"0.24": [-60, 0, 0],
						"0.32": [-60, 0, 0],
						"0.4": [-60, 0, 0],
						"0.48": [-60, 0, 0],
						"0.56": [-60, 0, 0],
						"0.64": [-60, 0, 0],
						"0.72": [-60, 0, 0],
						"0.8": [-60, 0, 0],
						"0.88": [-60, 0, 0],
						"0.96": [-60, 0, 0],
						"1.04": [-60, 0, 0],
						"1.12": [-60, 0, 0],
						"1.24": [-7.5, 0, 0],
						"1.36": [0, 0, 0]
					},
					"position": {
						"0.0": [0, 0, 0],
						"1.36": [0, 0, 0]
					}
				},
				"RightArm": {
					"rotation": {
						"0.0": [0, 0, 0],
						"0.08": [-237.5, 0, 0],
						"0.24": [-60, 0, 0],
						"0.32": [-60, 0, 0],
						"0.4": [-60, 0, 0],
						"0.48": [-60, 0, 0],
						"0.56": [-60, 0, 0],
						"0.64": [-60, 0, 0],
						"0.72": [-60, 0, 0],
						"0.8": [-60, 0, 0],
						"0.88": [-60, 0, 0],
						"0.96": [-60, 0, 0],
						"1.04": [-60, 0, 0],
						"1.12": [-60, 0, 0],
						"1.24": [-15, 0, 0],
						"1.36": [0, 0, 0]
					},
					"position": {
						"0.0": [0, 0, 0],
						"1.36": [0, 0, 0]
					}
				},
				"LeftLeg": {
					"rotation": {
						"0.0": [0, 0, 0],
						"0.08": [15, 0, 0],
						"0.24": [-108.75, 0, 0],
						"0.32": [-108.75, 0, 0],
						"0.4": [-108.75, 0, 0],
						"0.48": [-108.75, 0, 0],
						"0.56": [-108.75, 0, 0],
						"0.64": [-108.75, 0, 0],
						"0.72": [-108.75, 0, 0],
						"0.8": [-108.75, 0, 0],
						"0.88": [-108.75, 0, 0],
						"0.96": [-108.75, 0, 0],
						"1.04": [-108.75, 0, 0],
						"1.12": [-108.75, 0, 0],
						"1.24": [-41.88, 0, 0],
						"1.36": [0, 0, 0]
					},
					"position": {
						"0.0": [0, 0, 0],
						"0.08": [0, 1, 0],
						"0.24": [0, 0, 0],
						"0.32": [0, 0, 0],
						"0.4": [0, 0, 0],
						"0.48": [0, 0, 0],
						"0.56": [0, 0, 0],
						"0.64": [0, 0, 0],
						"0.72": [0, 0, 0],
						"0.8": [0, 0, 0],
						"0.88": [0, 0, 0],
						"0.96": [0, 0, 0],
						"1.04": [0, 0, 0],
						"1.12": [0, 0, 0],
						"1.24": [0, 0, 0],
						"1.36": [0, 0, 0]
					}
				},
				"RightLeg": {
					"rotation": {
						"0.0": [0, 0, 0],
						"0.08": [15, 0, 0],
						"0.24": [-108.75, 0, 0],
						"0.32": [-108.75, 0, 0],
						"0.4": [-108.75, 0, 0],
						"0.48": [-108.75, 0, 0],
						"0.56": [-108.75, 0, 0],
						"0.64": [-108.75, 0, 0],
						"0.72": [-108.75, 0, 0],
						"0.8": [-108.75, 0, 0],
						"0.88": [-108.75, 0, 0],
						"0.96": [-108.75, 0, 0],
						"1.04": [-108.75, 0, 0],
						"1.12": [-108.75, 0, 0],
						"1.24": [-41.88, 0, 0],
						"1.36": [0, 0, 0]
					},
					"position": {
						"0.0": [0, 0, 0],
						"0.08": [0, 1, 0],
						"0.24": [0, 0, 0],
						"0.32": [0, 0, 0],
						"0.4": [0, 0, 0],
						"0.48": [0, 0, 0],
						"0.56": [0, 0, 0],
						"0.64": [0, 0, 0],
						"0.72": [0, 0, 0],
						"0.8": [0, 0, 0],
						"0.88": [0, 0, 0],
						"0.96": [0, 0, 0],
						"1.04": [0, 0, 0],
						"1.12": [0, 0, 0],
						"1.24": [0, 0, 0],
						"1.36": [0, 0, 0]
					}
				}
			}
		},
		"staff": {
			"loop": "hold_on_last_frame",
			"animation_length": 0.6,
			"bones": {
				"Body": {
					"rotation": {
						"0.0": [0, 0, 0],
						"0.2": [0, 5, 0],
						"0.4": [0, -5, 0],
						"0.6": [0, 0, 0]
					},
					"position": {
						"0.0": [0, 0, 0],
						"0.2": [0, 0, 1.5],
						"0.4": [0, 0, -2.17],
						"0.6": [0, 0, 0]
					}
				},
				"LeftArm": {
					"rotation": {
						"0.0": [0, 0, 0],
						"0.2": [17.5, 0, 0],
						"0.4": [27.5, 0, 0],
						"0.6": [0, 0, 0]
					},
					"position": {
						"0.0": [0, 0, 0],
						"0.6": [0, 0, 0]
					}
				},
				"RightArm": {
					"rotation": {
						"0.0": [0, 0, 0],
						"0.2": [-152.5, 0, 0],
						"0.4": [-20, 0, 0],
						"0.6": [0, 0, 0]
					},
					"position": {
						"0.0": [0, 0, 0],
						"0.6": [0, 0, 0]
					}
				},
				"LeftLeg": {
					"rotation": {
						"0.0": [0, 0, 0],
						"0.2": [-7.5, -5, 0],
						"0.4": [10, -5, 0],
						"0.6": [0, 0, 0]
					},
					"position": {
						"0.0": [0, 0, 0],
						"0.6": [0, 0, 0]
					}
				},
				"RightLeg": {
					"rotation": {
						"0.0": [0, 0, 0],
						"0.2": [10, 0, 0],
						"0.4": [-20, 0, 0],
						"0.6": [0, 0, 0]
					},
					"position": {
						"0.0": [0, 0, 0],
						"0.28": [0, 0.63, -0.94],
						"0.4": [0, -0.5, -1.25],
						"0.6": [0, 0, 0]
					}
				}
			}
		},
		"staff_use": {
			"animation_length": 0.8,
			"bones": {
				"Body": {
					"rotation": {
						"0.0": [0, 0, 0],
						"0.16": [7.5, 35, 0],
						"0.4": [2.5, -20, 0],
						"0.48": [2.5, -20, 0],
						"0.8": [0, 0, 0]
					},
					"position": {
						"0.0": [0, 0, 0],
						"0.16": [0, -0.6, 0],
						"0.4": [0, -0.25, 0],
						"0.8": [0, 0, 0]
					}
				},
				"Head": {
					"rotation": {
						"0.0": [0, 0, 0],
						"0.16": [10, 0, 0],
						"0.8": [0, 0, 0]
					},
					"position": {
						"0.0": [0, 0, 0],
						"0.8": [0, 0, 0]
					}
				},
				"LeftArm": {
					"rotation": {
						"0.0": [0, 0, 0],
						"0.16": [-25, 7.5, 10],
						"0.4": [2.5, 7.5, -7.5],
						"0.48": [20, 7.5, -20],
						"0.8": [0, 0, 0]
					},
					"position": {
						"0.0": [0, 0, 0],
						"0.8": [0, 0, 0]
					}
				},
				"RightArm": {
					"rotation": {
						"0.0": [0, 0, 0],
						"0.16": [-77.5, 0, 0],
						"0.4": [-87.5, -10, 0],
						"0.48": [-92.5, 0, 0],
						"0.8": [0, 0, 0]
					},
					"position": {
						"0.0": [0, 0, 0],
						"0.16": [0, 0, 4],
						"0.4": [0, -0.5, -3],
						"0.48": [0, -0.5, -2],
						"0.8": [0, 0, 0]
					}
				},
				"LeftLeg": {
					"rotation": {
						"0.0": [0, 0, 0],
						"0.16": [-17.5, 0, 0],
						"0.4": [7.5, 0, 0],
						"0.48": [7.5, 0, 0],
						"0.8": [0, 0, 0]
					},
					"position": {
						"0.0": [0, 0, 0],
						"0.16": [0, 0.25, -1.5],
						"0.4": [0, 0.75, 1],
						"0.48": [0, 0.75, 1],
						"0.8": [0, 0, 0]
					}
				},
				"RightLeg": {
					"rotation": {
						"0.0": [0, 0, 0],
						"0.16": [10, 0, 0],
						"0.4": [-12.5, 0, 0],
						"0.48": [-12.5, 0, 0],
						"0.8": [0, 0, 0]
					},
					"position": {
						"0.0": [0, 0, 0],
						"0.16": [0, 0, 1.25],
						"0.4": [0, 0.25, -1.75],
						"0.48": [0, 0.25, -1.75],
						"0.8": [0, 0, 0]
					}
				}
			}
		}
	}
}